{"v":"4.8.0","meta":{"g":"LottieFiles AE 3.5.4","a":"","k":"","d":"","tc":""},"fr":24,"ip":0,"op":65,"w":1100,"h":1300,"nm":"Stepper Machine","ddd":0,"assets":[],"layers":[{"ddd":0,"ind":1,"ty":3,"nm":"scale","sr":1,"ks":{"o":{"a":0,"k":0,"ix":11},"r":{"a":0,"k":0,"ix":10},"p":{"a":0,"k":[350,589.98,0],"ix":2},"a":{"a":0,"k":[50,50,0],"ix":1},"s":{"a":0,"k":[120,120,100],"ix":6}},"ao":0,"ip":0,"op":111,"st":0,"bm":0},{"ddd":0,"ind":2,"ty":3,"nm":"position","parent":1,"sr":1,"ks":{"o":{"a":0,"k":0,"ix":11},"r":{"a":0,"k":0,"ix":10},"p":{"a":1,"k":[{"i":{"x":0.667,"y":1},"o":{"x":0.333,"y":0},"t":1,"s":[50,50,0],"to":[0,0,0],"ti":[0,0,0]},{"i":{"x":0.667,"y":1},"o":{"x":0.333,"y":0},"t":16.605,"s":[50,20,0],"to":[0,0,0],"ti":[0,0,0]},{"i":{"x":0.667,"y":0.667},"o":{"x":0.333,"y":0.333},"t":31.633,"s":[50,50,0],"to":[0,0,0],"ti":[0,0,0]},{"i":{"x":0.667,"y":1},"o":{"x":0.333,"y":0},"t":33.367,"s":[50,50,0],"to":[0,0,0],"ti":[0,0,0]},{"i":{"x":0.667,"y":1},"o":{"x":0.333,"y":0},"t":48.395,"s":[50,20,0],"to":[0,0,0],"ti":[0,0,0]},{"t":64,"s":[50,50,0]}],"ix":2},"a":{"a":0,"k":[50,50,0],"ix":1},"s":{"a":0,"k":[100,100,100],"ix":6}},"ao":0,"ip":0,"op":111,"st":0,"bm":0},{"ddd":0,"ind":3,"ty":4,"nm":"Arm","parent":11,"sr":1,"ks":{"o":{"a":0,"k":100,"ix":11},"r":{"a":1,"k":[{"i":{"x":[0.833],"y":[1]},"o":{"x":[0.333],"y":[0]},"t":1,"s":[-3]},{"i":{"x":[0.667],"y":[1]},"o":{"x":[0.167],"y":[0]},"t":16.605,"s":[-15]},{"i":{"x":[0.667],"y":[1]},"o":{"x":[0.333],"y":[0]},"t":31.633,"s":[-3]},{"i":{"x":[0.833],"y":[1]},"o":{"x":[0.333],"y":[0]},"t":33.367,"s":[-3]},{"i":{"x":[0.667],"y":[1]},"o":{"x":[0.167],"y":[0]},"t":48.395,"s":[-15]},{"t":64,"s":[-3]}],"ix":10},"p":{"a":1,"k":[{"i":{"x":0.667,"y":1},"o":{"x":0.333,"y":0},"t":1,"s":[47.359,52.697,0],"to":[0,0,0],"ti":[0,0,0]},{"i":{"x":0.667,"y":1},"o":{"x":0.333,"y":0},"t":16.605,"s":[48.568,57.549,0],"to":[0,0,0],"ti":[0,0,0]},{"i":{"x":0.667,"y":0.667},"o":{"x":0.333,"y":0.333},"t":31.633,"s":[47.359,52.697,0],"to":[0,0,0],"ti":[0,0,0]},{"i":{"x":0.667,"y":1},"o":{"x":0.333,"y":0},"t":33.367,"s":[47.359,52.697,0],"to":[0,0,0],"ti":[0,0,0]},{"i":{"x":0.667,"y":1},"o":{"x":0.333,"y":0},"t":48.395,"s":[48.568,57.549,0],"to":[0,0,0],"ti":[0,0,0]},{"t":64,"s":[47.359,52.697,0]}],"ix":2},"a":{"a":0,"k":[39.02,38.831,0],"ix":1},"s":{"a":0,"k":[100,100,100],"ix":6}},"ao":0,"shapes":[{"ty":"gr","it":[{"ind":0,"ty":"sh","ix":1,"ks":{"a":1,"k":[{"i":{"x":0.833,"y":0.712},"o":{"x":0.167,"y":0},"t":1,"s":[{"i":[[-6.917,-9.748],[-0.918,-5.501],[1.145,-1.944],[5.591,11.541],[-0.396,22.865],[4.169,24.068],[-6.273,9.429]],"o":[[15.954,22.485],[6.113,36.634],[-6.067,10.301],[-2.82,-5.822],[0.422,-24.32],[-2.002,-11.56],[17.271,-25.96]],"v":[[29.037,-78.421],[27.138,-24.415],[27.088,70.824],[-17.099,74.153],[-30.327,-2.453],[-34.183,-39.786],[-26.562,-76.49]],"c":true}]},{"i":{"x":0.833,"y":1},"o":{"x":0.167,"y":0.288},"t":16.605,"s":[{"i":[[-6.917,-9.748],[-0.918,-5.501],[1.145,-1.944],[5.591,11.541],[-0.396,22.865],[4.169,24.068],[-6.273,9.429]],"o":[[15.954,22.485],[6.113,36.634],[-6.067,10.301],[-2.82,-5.822],[0.422,-24.32],[-2.002,-11.56],[17.271,-25.96]],"v":[[29.037,-78.421],[27.138,-24.415],[22.907,91.169],[-20.096,89.994],[-30.327,-2.453],[-34.183,-39.786],[-26.562,-76.49]],"c":true}]},{"i":{"x":0.833,"y":1},"o":{"x":0.167,"y":0},"t":31.633,"s":[{"i":[[-6.917,-9.748],[-0.918,-5.501],[1.145,-1.944],[5.591,11.541],[-0.396,22.865],[4.169,24.068],[-6.273,9.429]],"o":[[15.954,22.485],[6.113,36.634],[-6.067,10.301],[-2.82,-5.822],[0.422,-24.32],[-2.002,-11.56],[17.271,-25.96]],"v":[[29.037,-78.421],[27.138,-24.415],[27.088,70.824],[-17.099,74.153],[-30.327,-2.453],[-34.183,-39.786],[-26.562,-76.49]],"c":true}]},{"i":{"x":0.833,"y":0.712},"o":{"x":0.167,"y":0},"t":33.367,"s":[{"i":[[-6.917,-9.748],[-0.918,-5.501],[1.145,-1.944],[5.591,11.541],[-0.396,22.865],[4.169,24.068],[-6.273,9.429]],"o":[[15.954,22.485],[6.113,36.634],[-6.067,10.301],[-2.82,-5.822],[0.422,-24.32],[-2.002,-11.56],[17.271,-25.96]],"v":[[29.037,-78.421],[27.138,-24.415],[27.088,70.824],[-17.099,74.153],[-30.327,-2.453],[-34.183,-39.786],[-26.562,-76.49]],"c":true}]},{"i":{"x":0.833,"y":1},"o":{"x":0.167,"y":0.288},"t":48.395,"s":[{"i":[[-6.917,-9.748],[-0.918,-5.501],[1.145,-1.944],[5.591,11.541],[-0.396,22.865],[4.169,24.068],[-6.273,9.429]],"o":[[15.954,22.485],[6.113,36.634],[-6.067,10.301],[-2.82,-5.822],[0.422,-24.32],[-2.002,-11.56],[17.271,-25.96]],"v":[[29.037,-78.421],[27.138,-24.415],[22.907,91.169],[-20.096,89.994],[-30.327,-2.453],[-34.183,-39.786],[-26.562,-76.49]],"c":true}]},{"t":64,"s":[{"i":[[-6.917,-9.748],[-0.918,-5.501],[1.145,-1.944],[5.591,11.541],[-0.396,22.865],[4.169,24.068],[-6.273,9.429]],"o":[[15.954,22.485],[6.113,36.634],[-6.067,10.301],[-2.82,-5.822],[0.422,-24.32],[-2.002,-11.56],[17.271,-25.96]],"v":[[29.037,-78.421],[27.138,-24.415],[27.088,70.824],[-17.099,74.153],[-30.327,-2.453],[-34.183,-39.786],[-26.562,-76.49]],"c":true}]}],"ix":2},"nm":"Path 1","mn":"ADBE Vector Shape - Group","hd":false},{"ty":"fl","c":{"a":0,"k":[0.67,0.67,0.67,1],"ix":4},"o":{"a":0,"k":100,"ix":5},"r":1,"bm":0,"nm":"Fill 1","mn":"ADBE Vector Graphic - Fill","hd":false},{"ty":"tr","p":{"a":0,"k":[38.927,98.959],"ix":2},"a":{"a":0,"k":[0,0],"ix":1},"s":{"a":0,"k":[100,100],"ix":3},"r":{"a":0,"k":0,"ix":6},"o":{"a":0,"k":100,"ix":7},"sk":{"a":0,"k":0,"ix":4},"sa":{"a":0,"k":0,"ix":5},"nm":"Transform"}],"nm":"Group 2","np":2,"cix":2,"bm":0,"ix":1,"mn":"ADBE Vector Group","hd":false}],"ip":0,"op":111,"st":0,"bm":0},{"ddd":0,"ind":4,"ty":4,"nm":"Forearm","parent":5,"sr":1,"ks":{"o":{"a":0,"k":100,"ix":11},"r":{"a":1,"k":[{"i":{"x":[0.833],"y":[1]},"o":{"x":[0.333],"y":[0]},"t":1,"s":[167.946]},{"i":{"x":[0.667],"y":[1]},"o":{"x":[0.167],"y":[0]},"t":16.605,"s":[153.946]},{"i":{"x":[0.667],"y":[1]},"o":{"x":[0.333],"y":[0]},"t":31.633,"s":[167.946]},{"i":{"x":[0.833],"y":[1]},"o":{"x":[0.333],"y":[0]},"t":33.367,"s":[167.946]},{"i":{"x":[0.667],"y":[1]},"o":{"x":[0.167],"y":[0]},"t":48.395,"s":[153.946]},{"t":64,"s":[167.946]}],"ix":10},"p":{"a":0,"k":[20.462,68.941,0],"ix":2},"a":{"a":0,"k":[54.342,130.005,0],"ix":1},"s":{"a":0,"k":[-147.849,147.849,100],"ix":6}},"ao":0,"shapes":[{"ty":"gr","it":[{"ind":0,"ty":"sh","ix":1,"ks":{"a":0,"k":{"i":[[0.77,-9.675],[-5.853,-5.119],[-3.659,17.255],[15.029,25.24],[21.284,-13.108]],"o":[[-2.783,34.956],[1.026,0.897],[-6.179,-29.502],[-2.251,-3.78],[-0.198,0.122]],"v":[[-29.762,-41.657],[10.234,70.051],[33.12,59.861],[15.263,-49.21],[-24.037,-60.817]],"c":true},"ix":2},"nm":"Path 1","mn":"ADBE Vector Shape - Group","hd":false},{"ty":"fl","c":{"a":0,"k":[0.67,0.67,0.67,1],"ix":4},"o":{"a":0,"k":100,"ix":5},"r":1,"bm":0,"nm":"Fill 1","mn":"ADBE Vector Graphic - Fill","hd":false},{"ty":"tr","p":{"a":0,"k":[33.967,68.847],"ix":2},"a":{"a":0,"k":[0,0],"ix":1},"s":{"a":0,"k":[100,100],"ix":3},"r":{"a":0,"k":0,"ix":6},"o":{"a":0,"k":100,"ix":7},"sk":{"a":0,"k":0,"ix":4},"sa":{"a":0,"k":0,"ix":5},"nm":"Transform"}],"nm":"Group 2","np":2,"cix":2,"bm":0,"ix":1,"mn":"ADBE Vector Group","hd":false}],"ip":0,"op":111,"st":0,"bm":0},{"ddd":0,"ind":5,"ty":4,"nm":"hand","parent":1,"sr":1,"ks":{"o":{"a":0,"k":100,"ix":11},"r":{"a":0,"k":154.26,"ix":10},"p":{"a":0,"k":[135.703,13.515,0],"ix":2},"a":{"a":0,"k":[23.967,72.329,0],"ix":1},"s":{"a":0,"k":[-67.636,67.636,100],"ix":6}},"ao":0,"shapes":[{"ty":"gr","it":[{"ind":0,"ty":"sh","ix":1,"ks":{"a":0,"k":{"i":[[-0.438,0.193],[-1.202,-0.003],[0.28,-0.565],[-3.399,0.636],[-2.553,-2.332],[0.019,-0.211],[0.082,0.194],[-0.665,0.007],[-0.851,-3.55],[-0.203,-0.297],[-0.946,0.042],[-2.504,-0.781],[0.935,-5.407],[0.718,-3.74],[-0.814,-2.972],[-0.36,-1.124],[2.24,-3.373],[3.901,-2.26],[5.083,-0.286],[3.395,5.232],[1.019,5.64],[-0.998,8.526],[-0.041,4.57],[-0.637,1.573],[-0.979,0.717]],"o":[[1.097,-0.485],[0.317,0.001],[1.537,-3.098],[3.399,-0.636],[0.157,0.143],[-0.019,0.212],[-0.422,-0.996],[3.65,-0.036],[0.084,0.348],[0.678,0.993],[2.62,-0.119],[5.874,1.832],[-0.641,3.709],[-0.56,2.91],[0.312,1.139],[1.332,4.156],[-2.493,3.753],[-3.035,1.759],[-6.121,0.345],[-6.632,-10.223],[-1.525,-8.444],[0.529,-4.52],[0.015,-1.674],[0.455,-1.124],[0.392,-0.287]],"v":[[-26.155,-36.178],[-22.641,-36.866],[-18.01,-35.656],[-11.281,-42.04],[-1.658,-39.298],[-1.354,-38.765],[-1.009,-38.476],[6.038,-40.848],[14.034,-34.607],[14.387,-33.597],[17.965,-33.525],[25.771,-32.974],[32.057,-18.988],[28.632,-8.243],[27.56,0.873],[28.858,4.165],[25.061,16.891],[15.322,26.096],[-2.542,42.331],[-29.128,36.889],[-31.151,11.521],[-31.995,-14.122],[-30.323,-27.678],[-29.612,-32.626],[-27.405,-35.46]],"c":true},"ix":2},"nm":"Path 1","mn":"ADBE Vector Shape - Group","hd":false},{"ty":"fl","c":{"a":0,"k":[0.67,0.67,0.67,1],"ix":4},"o":{"a":0,"k":100,"ix":5},"r":1,"bm":0,"nm":"Fill 1","mn":"ADBE Vector Graphic - Fill","hd":false},{"ty":"tr","p":{"a":0,"k":[33.242,42.926],"ix":2},"a":{"a":0,"k":[0,0],"ix":1},"s":{"a":0,"k":[100,100],"ix":3},"r":{"a":0,"k":0,"ix":6},"o":{"a":0,"k":100,"ix":7},"sk":{"a":0,"k":0,"ix":4},"sa":{"a":0,"k":0,"ix":5},"nm":"Transform"}],"nm":"Group 1","np":2,"cix":2,"bm":0,"ix":1,"mn":"ADBE Vector Group","hd":false}],"ip":0,"op":111,"st":0,"bm":0},{"ddd":0,"ind":6,"ty":4,"nm":"Handle_up","parent":8,"sr":1,"ks":{"o":{"a":0,"k":100,"ix":11},"r":{"a":0,"k":0,"ix":10},"p":{"a":0,"k":[408.587,257.399,0],"ix":2},"a":{"a":0,"k":[330.734,69.552,0],"ix":1},"s":{"a":0,"k":[100,100,100],"ix":6}},"ao":0,"shapes":[{"ty":"gr","it":[{"ind":0,"ty":"sh","ix":1,"ks":{"a":0,"k":{"i":[[6.977,-0.598],[4.212,-0.361],[11.209,-0.961],[16.064,-1.377],[18.776,-1.609],[19.345,-1.658],[0,0],[14.012,-1.201],[8.219,-0.704],[1.246,-0.11],[13.342,-6.212],[9.768,-10.248],[5.826,-14.086],[1.366,-6.58],[-6.872,-1.565],[-1.42,6.847],[-1.381,4.107],[-2.213,3.466],[-0.577,0.782],[-2.931,2.817],[-1.542,1.321],[-0.828,0.667],[-0.303,0.24],[-2.529,1.882],[-7.483,3.3],[-1.483,0.589],[-0.64,0.247],[-1.113,0.387],[-2.285,0.626],[-4.757,0.642],[1.108,-0.149],[-4.234,0.363],[-7.83,0.671],[-11.856,1.016],[0,0],[-16.047,1.376],[-16.246,1.393],[-15.112,1.295],[-12.796,1.097],[-9.256,0.794],[-4.383,0.398],[-0.186,0.016],[-2.461,2.461],[0.139,3.114]],"o":[[-4.213,0.361],[-11.21,0.961],[-16.064,1.376],[-18.776,1.609],[-19.344,1.658],[0,0],[-14.012,1.201],[-8.219,0.704],[-1.246,0.107],[-14.661,1.29],[-12.842,5.979],[-10.555,11.071],[-2.569,6.212],[-1.324,6.385],[6.253,1.425],[0.881,-4.243],[0.665,-1.979],[1.048,-1.64],[-2.068,2.8],[1.463,-1.407],[0.808,-0.691],[0.302,-0.243],[1.654,-1.315],[6.566,-4.885],[2.056,-0.906],[0.638,-0.254],[1.1,-0.425],[2.237,-0.779],[4.63,-1.267],[-1.108,0.149],[4.216,-0.544],[7.831,-0.672],[11.857,-1.016],[0,0],[16.048,-1.376],[16.246,-1.392],[15.112,-1.295],[12.795,-1.097],[9.255,-0.793],[4.384,-0.375],[0.186,-0.017],[3.37,-0.289],[2.168,-2.168],[-0.282,-6.294]],"v":[[213.88,-68.973],[201.242,-67.89],[167.612,-65.007],[119.42,-60.877],[63.093,-56.049],[5.06,-51.075],[-48.25,-46.506],[-90.286,-42.903],[-114.945,-40.79],[-118.683,-40.469],[-160.523,-29.306],[-194.985,-4.425],[-219.312,33.533],[-225.195,52.77],[-216.463,68.146],[-201.088,59.416],[-197.713,46.878],[-187.907,26.735],[-182.894,19.562],[-174.032,9.963],[-169.521,5.87],[-167.067,3.832],[-166.16,3.109],[-166.385,3.299],[-145.23,-8.919],[-146.322,-8.454],[-144.411,-9.215],[-141.092,-10.433],[-134.307,-12.542],[-120.21,-15.389],[-123.533,-14.942],[-110.831,-16.142],[-87.339,-18.156],[-51.771,-21.204],[-8.206,-24.938],[39.937,-29.065],[88.674,-33.242],[134.01,-37.127],[172.397,-40.418],[200.165,-42.798],[213.32,-43.925],[213.88,-43.973],[222.718,-47.634],[226.38,-56.473]],"c":true},"ix":2},"nm":"Path 1","mn":"ADBE Vector Shape - Group","hd":false},{"ty":"fl","c":{"a":0,"k":[0.61,0.61,0.61,1],"ix":4},"o":{"a":0,"k":100,"ix":5},"r":1,"bm":0,"nm":"Fill 1","mn":"ADBE Vector Graphic - Fill","hd":false},{"ty":"tr","p":{"a":0,"k":[330.284,69.821],"ix":2},"a":{"a":0,"k":[0,0],"ix":1},"s":{"a":0,"k":[100,100],"ix":3},"r":{"a":0,"k":0,"ix":6},"o":{"a":0,"k":100,"ix":7},"sk":{"a":0,"k":0,"ix":4},"sa":{"a":0,"k":0,"ix":5},"nm":"Transform"}],"nm":"Group 1","np":2,"cix":2,"bm":0,"ix":1,"mn":"ADBE Vector Group","hd":false}],"ip":0,"op":111,"st":0,"bm":0},{"ddd":0,"ind":7,"ty":4,"nm":"Handle","parent":8,"sr":1,"ks":{"o":{"a":0,"k":100,"ix":11},"r":{"a":0,"k":0,"ix":10},"p":{"a":0,"k":[356.824,510.583,0],"ix":2},"a":{"a":0,"k":[278.972,322.736,0],"ix":1},"s":{"a":0,"k":[100,100,100],"ix":6}},"ao":0,"shapes":[{"ty":"gr","it":[{"ind":0,"ty":"sh","ix":1,"ks":{"a":0,"k":{"i":[[6.977,-0.598],[5.447,-0.467],[14.283,-1.224],[0,0],[22.088,-1.893],[21.292,-1.825],[17.078,-1.464],[9.757,-0.836],[17.324,-10.876],[6.494,-31.238],[0.796,-3.896],[2.08,-10.173],[3.074,-15.036],[3.806,-18.618],[4.291,-20.984],[0,0],[0,0],[4.062,-19.869],[3.428,-16.766],[0,0],[0,0],[0.176,-0.864],[-6.884,-1.568],[-1.401,6.85],[-0.725,3.546],[-2.01,9.831],[-3.01,14.723],[-3.77,18.441],[-4.23,20.687],[-4.44,21.714],[-4.404,21.54],[-4.062,19.866],[-3.475,16.995],[-2.633,12.876],[-1.5,7.335],[-0.251,1.21],[-1.805,4.948],[-0.372,0.934],[-0.098,0.398],[-0.581,1.271],[-0.9,1.782],[-2.082,3.202],[-1.076,1.479],[-0.329,0.455],[0.005,-0.006],[-0.617,0.743],[-2.712,2.634],[-1.368,1.198],[-0.754,0.624],[1.382,-1.169],[-0.396,0.288],[-0.691,0.478],[-1.674,1.024],[-3.57,1.666],[-0.773,0.345],[-2.214,0.857],[-2.026,0.67],[-3.786,0.802],[-1.86,0.292],[-0.401,0.119],[-1.437,0.153],[-1.169,0.107],[-5.499,0.471],[0,0],[-19.693,1.688],[-21.972,1.884],[-21.166,1.814],[-17.26,1.479],[-10.019,0.858],[-1.34,0.115],[0.32,7.15]],"o":[[-5.447,0.467],[-14.283,1.224],[0,0],[-22.088,1.893],[-21.292,1.825],[-17.078,1.463],[-9.757,0.836],[-20.198,1.731],[-26.966,16.929],[-0.81,3.893],[-2.08,10.173],[-3.075,15.036],[-3.807,18.618],[-4.291,20.985],[0,0],[0,0],[-4.062,19.868],[-3.428,16.766],[0,0],[0,0],[-0.177,0.864],[-1.307,6.388],[6.237,1.421],[0.725,-3.546],[2.01,-9.83],[3.011,-14.722],[3.77,-18.44],[4.23,-20.687],[4.44,-21.713],[4.404,-21.539],[4.062,-19.866],[3.475,-16.995],[2.633,-12.876],[1.5,-7.336],[0.247,-1.212],[1.071,-5.155],[0.344,-0.945],[0.152,-0.382],[-0.003,0.011],[0.83,-1.815],[1.724,-3.409],[0.998,-1.533],[0.33,-0.455],[0.809,-1.117],[0.676,-0.686],[2.414,-2.909],[1.304,-1.267],[0.736,-0.645],[0.406,-0.336],[-1.469,1.243],[0.679,-0.493],[1.615,-1.115],[3.361,-2.054],[0.768,-0.358],[2.165,-0.967],[1.99,-0.769],[3.675,-1.216],[1.843,-0.391],[0.414,-0.065],[-0.002,0.001],[1.167,-0.123],[5.496,-0.501],[0,0],[19.694,-1.688],[21.972,-1.883],[21.166,-1.814],[17.261,-1.48],[10.019,-0.859],[1.34,-0.115],[6.498,-0.557],[-0.282,-6.294]],"v":[[265.547,-322.155],[249.205,-320.754],[206.356,-317.082],[147.057,-311.999],[80.793,-306.32],[16.918,-300.845],[-34.316,-296.454],[-63.588,-293.945],[-120.442,-276.186],[-173.531,-200.388],[-175.921,-188.7],[-182.161,-158.181],[-191.384,-113.073],[-202.804,-57.219],[-215.676,5.734],[-229.071,71.246],[-242.239,135.649],[-254.426,195.254],[-264.71,245.552],[-272.344,282.887],[-276.53,303.363],[-277.06,305.956],[-268.33,321.332],[-252.953,312.602],[-250.778,301.964],[-244.749,272.473],[-235.718,228.306],[-224.407,172.985],[-211.718,110.925],[-198.399,45.784],[-185.187,-18.835],[-173.001,-78.433],[-162.576,-129.419],[-154.678,-168.047],[-150.178,-190.054],[-149.436,-193.688],[-145.148,-208.864],[-144.073,-211.682],[-143.59,-212.877],[-144.012,-211.866],[-141.466,-217.279],[-135.751,-227.204],[-132.638,-231.723],[-131.636,-233.079],[-132.308,-232.219],[-130.458,-234.511],[-122.763,-242.834],[-118.754,-246.531],[-116.519,-248.436],[-115.162,-249.557],[-113.743,-250.599],[-111.687,-252.056],[-106.751,-255.265],[-96.343,-260.852],[-94.027,-261.899],[-93.879,-261.951],[-87.872,-264.141],[-76.669,-267.174],[-71.113,-268.198],[-69.817,-268.395],[-70.97,-268.238],[-67.47,-268.611],[-50.974,-270.026],[-8.807,-273.64],[50.273,-278.704],[116.19,-284.354],[179.688,-289.796],[231.47,-294.234],[261.527,-296.81],[265.547,-297.155],[278.047,-309.655]],"c":true},"ix":2},"nm":"Path 1","mn":"ADBE Vector Shape - Group","hd":false},{"ty":"fl","c":{"a":0,"k":[0.69,0.69,0.69,1],"ix":4},"o":{"a":0,"k":100,"ix":5},"r":1,"bm":0,"nm":"Fill 1","mn":"ADBE Vector Graphic - Fill","hd":false},{"ty":"tr","p":{"a":0,"k":[278.617,323.003],"ix":2},"a":{"a":0,"k":[0,0],"ix":1},"s":{"a":0,"k":[100,100],"ix":3},"r":{"a":0,"k":0,"ix":6},"o":{"a":0,"k":100,"ix":7},"sk":{"a":0,"k":0,"ix":4},"sa":{"a":0,"k":0,"ix":5},"nm":"Transform"}],"nm":"Group 2","np":2,"cix":2,"bm":0,"ix":1,"mn":"ADBE Vector Group","hd":false}],"ip":0,"op":111,"st":0,"bm":0},{"ddd":0,"ind":8,"ty":4,"nm":"Elliptical","parent":1,"sr":1,"ks":{"o":{"a":0,"k":100,"ix":11},"r":{"a":0,"k":0,"ix":10},"p":{"a":0,"k":[262,204.02,0],"ix":2},"a":{"a":0,"k":[361.544,435.661,0],"ix":1},"s":{"a":0,"k":[90,90,100],"ix":6}},"ao":0,"shapes":[{"ty":"gr","it":[{"ind":0,"ty":"sh","ix":1,"ks":{"a":0,"k":{"i":[[0,0],[0,0],[11.619,0],[0,0],[0,-8.359],[0,0]],"o":[[0,0],[-0.031,-11.27],[0,0],[-9.198,0],[0,0],[0,0]],"v":[[277.591,26.912],[277.496,-6.521],[256.417,-26.912],[-260.936,-26.912],[-277.591,-11.776],[-277.591,26.912]],"c":true},"ix":2},"nm":"Path 1","mn":"ADBE Vector Shape - Group","hd":false},{"ty":"fl","c":{"a":0,"k":[0.69,0.69,0.69,1],"ix":4},"o":{"a":0,"k":100,"ix":5},"r":1,"bm":0,"nm":"Fill 1","mn":"ADBE Vector Graphic - Fill","hd":false},{"ty":"tr","p":{"a":0,"k":[277.951,820.129],"ix":2},"a":{"a":0,"k":[0,0],"ix":1},"s":{"a":0,"k":[100,100],"ix":3},"r":{"a":0,"k":0,"ix":6},"o":{"a":0,"k":100,"ix":7},"sk":{"a":0,"k":0,"ix":4},"sa":{"a":0,"k":0,"ix":5},"nm":"Transform"}],"nm":"Group 1","np":2,"cix":2,"bm":0,"ix":1,"mn":"ADBE Vector Group","hd":false},{"ty":"gr","it":[{"ind":0,"ty":"sh","ix":1,"ks":{"a":0,"k":{"i":[[0.117,-2.272],[0,0],[0,0],[0,0],[1.857,-1.837],[0,0]],"o":[[0,0],[0,0],[0,0],[-2.607,-0.172],[0,0],[-1.617,1.6]],"v":[[-72.571,64.059],[-73.008,72.532],[73.008,-71.884],[65.812,-72.36],[58.792,-69.741],[-69.875,58.04]],"c":true},"ix":2},"nm":"Path 1","mn":"ADBE Vector Shape - Group","hd":false},{"ty":"fl","c":{"a":0,"k":[0.8824,0.8824,0.8824,1],"ix":4},"o":{"a":0,"k":100,"ix":5},"r":1,"bm":0,"nm":"Fill 1","mn":"ADBE Vector Graphic - Fill","hd":false},{"ty":"tr","p":{"a":0,"k":[629.113,72.781],"ix":2},"a":{"a":0,"k":[0,0],"ix":1},"s":{"a":0,"k":[100,100],"ix":3},"r":{"a":0,"k":0,"ix":6},"o":{"a":0,"k":100,"ix":7},"sk":{"a":0,"k":0,"ix":4},"sa":{"a":0,"k":0,"ix":5},"nm":"Transform"}],"nm":"Group 2","np":2,"cix":2,"bm":0,"ix":2,"mn":"ADBE Vector Group","hd":false},{"ty":"gr","it":[{"ind":0,"ty":"sh","ix":1,"ks":{"a":0,"k":{"i":[[3.887,3.93],[0,0],[0,0],[0,0],[3.811,-3.77],[0,0]],"o":[[0,0],[0,0],[0,0],[3.769,3.811],[0,0],[-3.931,3.887]],"v":[[-66.169,79.154],[-83.831,61.297],[62.186,-83.12],[80.062,-65.045],[79.986,-51.318],[-52.013,79.232]],"c":true},"ix":2},"nm":"Path 1","mn":"ADBE Vector Shape - Group","hd":false},{"ty":"fl","c":{"a":0,"k":[0.69,0.69,0.69,1],"ix":4},"o":{"a":0,"k":100,"ix":5},"r":1,"bm":0,"nm":"Fill 1","mn":"ADBE Vector Graphic - Fill","hd":false},{"ty":"tr","p":{"a":0,"k":[639.935,83.77],"ix":2},"a":{"a":0,"k":[0,0],"ix":1},"s":{"a":0,"k":[100,100],"ix":3},"r":{"a":0,"k":0,"ix":6},"o":{"a":0,"k":100,"ix":7},"sk":{"a":0,"k":0,"ix":4},"sa":{"a":0,"k":0,"ix":5},"nm":"Transform"}],"nm":"Group 3","np":2,"cix":2,"bm":0,"ix":3,"mn":"ADBE Vector Group","hd":false},{"ty":"gr","it":[{"ind":0,"ty":"sh","ix":1,"ks":{"a":0,"k":{"i":[[0,0],[0,0],[0,0],[-5.064,23.352]],"o":[[0,0],[0,0],[-1.686,7.738],[0,0]],"v":[[110.934,-381.767],[44.736,-357.57],[-109.248,358.545],[-51.805,358.415]],"c":true},"ix":2},"nm":"Path 1","mn":"ADBE Vector Shape - Group","hd":false},{"ty":"fl","c":{"a":0,"k":[0.69,0.69,0.69,1],"ix":4},"o":{"a":0,"k":100,"ix":5},"r":1,"bm":0,"nm":"Fill 1","mn":"ADBE Vector Graphic - Fill","hd":false},{"ty":"tr","p":{"a":0,"k":[573.391,439.556],"ix":2},"a":{"a":0,"k":[0,0],"ix":1},"s":{"a":0,"k":[100,100],"ix":3},"r":{"a":0,"k":0,"ix":6},"o":{"a":0,"k":100,"ix":7},"sk":{"a":0,"k":0,"ix":4},"sa":{"a":0,"k":0,"ix":5},"nm":"Transform"}],"nm":"Group 4","np":2,"cix":2,"bm":0,"ix":4,"mn":"ADBE Vector Group","hd":false},{"ty":"gr","it":[{"ind":0,"ty":"sh","ix":1,"ks":{"a":0,"k":{"i":[[0,0],[0,0],[0,0],[-30.91,0],[0,0]],"o":[[0,0],[0,0],[5.5,-30.187],[0,0],[0,0]],"v":[[75.617,137.965],[-137.46,137.965],[-96.688,-85.823],[-33.797,-137.966],[137.461,-137.966]],"c":true},"ix":2},"nm":"Path 1","mn":"ADBE Vector Shape - Group","hd":false},{"ty":"fl","c":{"a":0,"k":[0.69,0.69,0.69,1],"ix":4},"o":{"a":0,"k":100,"ix":5},"r":1,"bm":0,"nm":"Fill 1","mn":"ADBE Vector Graphic - Fill","hd":false},{"ty":"tr","p":{"a":0,"k":[425.33,655.252],"ix":2},"a":{"a":0,"k":[0,0],"ix":1},"s":{"a":0,"k":[100,100],"ix":3},"r":{"a":0,"k":0,"ix":6},"o":{"a":0,"k":100,"ix":7},"sk":{"a":0,"k":0,"ix":4},"sa":{"a":0,"k":0,"ix":5},"nm":"Transform"}],"nm":"Group 5","np":2,"cix":2,"bm":0,"ix":5,"mn":"ADBE Vector Group","hd":false},{"ty":"gr","it":[{"ind":0,"ty":"sh","ix":1,"ks":{"a":0,"k":{"i":[[0,0],[0,0],[0,0],[4.605,0],[0,0],[0,4.604]],"o":[[0,0],[0,0],[0,4.605],[0,0],[-4.604,-0.001],[0,0]],"v":[[-35.285,-13.047],[35.285,-13.047],[35.285,4.71],[26.947,13.047],[-26.949,13.039],[-35.285,4.702]],"c":true},"ix":2},"nm":"Path 1","mn":"ADBE Vector Shape - Group","hd":false},{"ty":"fl","c":{"a":0,"k":[0.69,0.69,0.69,1],"ix":4},"o":{"a":0,"k":100,"ix":5},"r":1,"bm":0,"nm":"Fill 1","mn":"ADBE Vector Graphic - Fill","hd":false},{"ty":"tr","p":{"a":0,"k":[520.256,857.872],"ix":2},"a":{"a":0,"k":[0,0],"ix":1},"s":{"a":0,"k":[100,100],"ix":3},"r":{"a":0,"k":0,"ix":6},"o":{"a":0,"k":100,"ix":7},"sk":{"a":0,"k":0,"ix":4},"sa":{"a":0,"k":0,"ix":5},"nm":"Transform"}],"nm":"Group 6","np":2,"cix":2,"bm":0,"ix":6,"mn":"ADBE Vector Group","hd":false},{"ty":"gr","it":[{"ind":0,"ty":"sh","ix":1,"ks":{"a":0,"k":{"i":[[0,0],[0,0],[0,0],[4.557,0.016],[0,0],[-0.037,4.574]],"o":[[0,0],[0,0],[-0.021,4.557],[0,0],[-4.574,-0.016],[0,0]],"v":[[-35.237,-12.953],[35.415,-13.035],[35.333,4.801],[27.047,13.02],[-27.152,12.823],[-35.378,4.5]],"c":true},"ix":2},"nm":"Path 1","mn":"ADBE Vector Shape - Group","hd":false},{"ty":"fl","c":{"a":0,"k":[0.69,0.69,0.69,1],"ix":4},"o":{"a":0,"k":100,"ix":5},"r":1,"bm":0,"nm":"Fill 1","mn":"ADBE Vector Graphic - Fill","hd":false},{"ty":"tr","p":{"a":0,"k":[35.665,857.861],"ix":2},"a":{"a":0,"k":[0,0],"ix":1},"s":{"a":0,"k":[100,100],"ix":3},"r":{"a":0,"k":0,"ix":6},"o":{"a":0,"k":100,"ix":7},"sk":{"a":0,"k":0,"ix":4},"sa":{"a":0,"k":0,"ix":5},"nm":"Transform"}],"nm":"Group 7","np":2,"cix":2,"bm":0,"ix":7,"mn":"ADBE Vector Group","hd":false}],"ip":0,"op":111,"st":0,"bm":0},{"ddd":0,"ind":9,"ty":4,"nm":"Hair","parent":10,"sr":1,"ks":{"o":{"a":0,"k":100,"ix":11},"r":{"a":0,"k":0,"ix":10},"p":{"a":0,"k":[36.455,57.456,0],"ix":2},"a":{"a":0,"k":[591.945,237.445,0],"ix":1},"s":{"a":0,"k":[-113.111,113.111,100],"ix":6}},"ao":0,"shapes":[{"ty":"gr","it":[{"ty":"gr","it":[{"ind":0,"ty":"sh","ix":1,"ks":{"a":0,"k":{"i":[[0,0],[0,0],[-3.25,-3.375],[0,0]],"o":[[0,0],[0,0],[1.048,1.088],[0,0]],"v":[[-70,-354.625],[-74,-353.5],[-67.5,-341.25],[-64.5,-341.75]],"c":true},"ix":2},"nm":"Path 1","mn":"ADBE Vector Shape - Group","hd":false},{"ty":"fl","c":{"a":0,"k":[0.31,0.31,0.31,1],"ix":4},"o":{"a":0,"k":100,"ix":5},"r":1,"bm":0,"nm":"Fill 1","mn":"ADBE Vector Graphic - Fill","hd":false},{"ty":"tr","p":{"a":0,"k":[0,0],"ix":2},"a":{"a":0,"k":[0,0],"ix":1},"s":{"a":0,"k":[100,100],"ix":3},"r":{"a":0,"k":0,"ix":6},"o":{"a":0,"k":100,"ix":7},"sk":{"a":0,"k":0,"ix":4},"sa":{"a":0,"k":0,"ix":5},"nm":"Transform"}],"nm":"Shape 3","np":3,"cix":2,"bm":0,"ix":1,"mn":"ADBE Vector Group","hd":false},{"ty":"gr","it":[{"ind":0,"ty":"sh","ix":1,"ks":{"a":0,"k":{"i":[[7.375,1.125],[5.625,-1],[-4.125,-2.5],[-4,-1.125],[0,0],[1.375,6]],"o":[[-7.375,-1.125],[-2.974,0.529],[4.125,2.5],[4,1.125],[0,0],[-0.883,-3.853]],"v":[[-58.125,-356.125],[-77.5,-352.75],[-73.25,-342.375],[-56.625,-341],[-50.375,-332.375],[-46.125,-342.375]],"c":true},"ix":2},"nm":"Path 1","mn":"ADBE Vector Shape - Group","hd":false},{"ty":"fl","c":{"a":0,"k":[0.09,0.09,0.09,1],"ix":4},"o":{"a":0,"k":100,"ix":5},"r":1,"bm":0,"nm":"Fill 1","mn":"ADBE Vector Graphic - Fill","hd":false},{"ty":"tr","p":{"a":0,"k":[0,0],"ix":2},"a":{"a":0,"k":[0,0],"ix":1},"s":{"a":0,"k":[100,100],"ix":3},"r":{"a":0,"k":0,"ix":6},"o":{"a":0,"k":100,"ix":7},"sk":{"a":0,"k":0,"ix":4},"sa":{"a":0,"k":0,"ix":5},"nm":"Transform"}],"nm":"Shape 2","np":3,"cix":2,"bm":0,"ix":2,"mn":"ADBE Vector Group","hd":false},{"ty":"gr","it":[{"ind":0,"ty":"sh","ix":1,"ks":{"a":0,"k":{"i":[[24.75,-1.125],[0,0],[-13.75,-1.25],[0,0]],"o":[[-24.75,1.125],[0,0],[13.75,1.25],[0,0]],"v":[[-98,-358.125],[-128.5,-340.125],[-93.625,-343.625],[-63.32,-336.625]],"c":true},"ix":2},"nm":"Path 1","mn":"ADBE Vector Shape - Group","hd":false},{"ty":"fl","c":{"a":0,"k":[0.09,0.09,0.09,1],"ix":4},"o":{"a":0,"k":100,"ix":5},"r":1,"bm":0,"nm":"Fill 1","mn":"ADBE Vector Graphic - Fill","hd":false},{"ty":"tr","p":{"a":0,"k":[0,0],"ix":2},"a":{"a":0,"k":[0,0],"ix":1},"s":{"a":0,"k":[100,100],"ix":3},"r":{"a":0,"k":0,"ix":6},"o":{"a":0,"k":100,"ix":7},"sk":{"a":0,"k":0,"ix":4},"sa":{"a":0,"k":0,"ix":5},"nm":"Transform"}],"nm":"Shape 1","np":3,"cix":2,"bm":0,"ix":3,"mn":"ADBE Vector Group","hd":false},{"ty":"tr","p":{"a":0,"k":[582.312,207.105],"ix":2},"a":{"a":0,"k":[-95.438,-347.395],"ix":1},"s":{"a":0,"k":[117,117],"ix":3},"r":{"a":0,"k":0,"ix":6},"o":{"a":0,"k":100,"ix":7},"sk":{"a":0,"k":0,"ix":4},"sa":{"a":0,"k":0,"ix":5},"nm":"Transform"}],"nm":"group 1","np":3,"cix":2,"bm":0,"ix":1,"mn":"ADBE Vector Group","hd":false},{"ty":"gr","it":[{"ty":"gr","it":[{"ind":0,"ty":"sh","ix":1,"ks":{"a":0,"k":{"i":[[0.243,2.214],[-2.283,3.035],[0.051,0.145],[-3.512,0.92],[0.143,-1.855],[-3.269,-4.857],[0.892,-4.845],[-1.227,0.235],[-0.724,3.262],[-2.156,1.133],[-2.175,-1.826],[-0.872,-2.526],[-0.016,-0.325],[1.219,-2.467],[1.624,-2.308],[-0.715,-1.09],[-2.29,-2.723]],"o":[[-0.119,-1.085],[18.724,-24.888],[-8.053,-22.831],[5.625,-1.474],[-0.44,5.709],[2.808,4.172],[1.805,0.327],[0.201,-0.866],[0.451,-2.037],[2.515,-1.32],[1.193,1.002],[0.106,0.309],[0.138,2.749],[-0.78,1.58],[-0.75,1.067],[2.287,3.49],[1.606,1.91]],"v":[[41.907,52.392],[49.884,35.712],[56.384,-11.067],[-16.458,-26.648],[-10.533,-8.038],[-5.066,5.16],[-0.02,15.303],[5.484,17.553],[7.141,12.647],[11.376,7.533],[19.178,8.228],[22.454,13.346],[22.633,14.309],[20.999,22.264],[15.754,29.416],[20.473,36.304],[28.142,47.358]],"c":true},"ix":2},"nm":"Path 1","mn":"ADBE Vector Shape - Group","hd":false},{"ty":"fl","c":{"a":0,"k":[0.21,0.21,0.21,1],"ix":4},"o":{"a":0,"k":100,"ix":5},"r":1,"bm":0,"nm":"Fill 1","mn":"ADBE Vector Graphic - Fill","hd":false},{"ty":"tr","p":{"a":0,"k":[38.246,50.829],"ix":2},"a":{"a":0,"k":[0,0],"ix":1},"s":{"a":0,"k":[100,100],"ix":3},"r":{"a":0,"k":0,"ix":6},"o":{"a":0,"k":100,"ix":7},"sk":{"a":0,"k":0,"ix":4},"sa":{"a":0,"k":0,"ix":5},"nm":"Transform"}],"nm":"Group 1","np":2,"cix":2,"bm":0,"ix":1,"mn":"ADBE Vector Group","hd":false},{"ty":"tr","p":{"a":0,"k":[581.017,232.283],"ix":2},"a":{"a":0,"k":[49.651,50.301],"ix":1},"s":{"a":0,"k":[90,90],"ix":3},"r":{"a":0,"k":0,"ix":6},"o":{"a":0,"k":100,"ix":7},"sk":{"a":0,"k":0,"ix":4},"sa":{"a":0,"k":0,"ix":5},"nm":"Transform"}],"nm":"group ","np":1,"cix":2,"bm":0,"ix":2,"mn":"ADBE Vector Group","hd":false}],"ip":0,"op":111,"st":0,"bm":0},{"ddd":0,"ind":10,"ty":4,"nm":"Head_skin","parent":14,"sr":1,"ks":{"o":{"a":0,"k":100,"ix":11},"r":{"a":0,"k":0,"ix":10},"p":{"a":0,"k":[46.12,2.278,0],"ix":2},"a":{"a":0,"k":[54.145,57.019,0],"ix":1},"s":{"a":0,"k":[100,100.217,100],"ix":6}},"ao":0,"shapes":[{"ty":"gr","it":[{"ind":0,"ty":"sh","ix":1,"ks":{"a":0,"k":{"i":[[-5.86,-13.59],[-0.57,-1.179],[-3.05,-4.189],[-8.941,-3.58],[-10.806,0],[-2.541,0.627],[-0.301,3.034],[0,4.462],[-0.109,0.013],[0.398,2.198],[0,0],[0.352,2.426],[0.557,2.631],[5.092,5.338],[12.61,-0.581],[2.12,-6.681]],"o":[[0.51,1.2],[2.51,5.18],[1.58,2.18],[9.963,3.989],[2.587,0],[3.084,-0.76],[0.441,-4.448],[0.017,-0.922],[6.33,-0.76],[-0.683,-3.771],[-0.677,-2.341],[-0.386,-2.661],[-1.513,-7.138],[-8.321,-8.723],[-17.58,0.809],[-2.62,14.88]],"v":[[-36.525,16.714],[-34.905,20.284],[-26.495,35.294],[-9.204,44.896],[23.01,51.721],[30.79,51.351],[35.376,45.442],[36.519,32.02],[36.505,22.044],[44.34,18.782],[35.305,-0.764],[34.384,-8.383],[32.983,-16.325],[23.716,-34.745],[-8.954,-51.396],[-42.175,-26.854]],"c":true},"ix":2},"nm":"Path 1","mn":"ADBE Vector Shape - Group","hd":false},{"ty":"fl","c":{"a":0,"k":[0.67,0.67,0.67,1],"ix":4},"o":{"a":0,"k":100,"ix":5},"r":1,"bm":0,"nm":"Fill 1","mn":"ADBE Vector Graphic - Fill","hd":false},{"ty":"tr","p":{"a":0,"k":[63.244,62.015],"ix":2},"a":{"a":0,"k":[0,0],"ix":1},"s":{"a":0,"k":[100,100],"ix":3},"r":{"a":0,"k":0,"ix":6},"o":{"a":0,"k":100,"ix":7},"sk":{"a":0,"k":0,"ix":4},"sa":{"a":0,"k":0,"ix":5},"nm":"Transform"}],"nm":"Group 1","np":2,"cix":2,"bm":0,"ix":1,"mn":"ADBE Vector Group","hd":false}],"ip":0,"op":111,"st":0,"bm":0},{"ddd":0,"ind":11,"ty":4,"nm":"Shirt","parent":20,"sr":1,"ks":{"o":{"a":0,"k":100,"ix":11},"r":{"a":0,"k":0,"ix":10},"p":{"a":0,"k":[44.683,-52.019,0],"ix":2},"a":{"a":0,"k":[66.764,117.418,0],"ix":1},"s":{"a":0,"k":[100,100,100],"ix":6}},"ao":0,"shapes":[{"ty":"gr","it":[{"ind":0,"ty":"sh","ix":1,"ks":{"a":0,"k":{"i":[[-2.048,-7.378],[4.57,-31.954],[-24.209,0],[0,0],[-1.106,14.962],[10.131,9.655],[17.062,2.861],[5.745,-12.508]],"o":[[3.955,14.25],[23.093,4.228],[30.172,0],[0,0],[1.092,-14.783],[-8.371,-7.979],[-22.521,-3.776],[-21.133,46.007]],"v":[[-51.014,31.977],[-44.178,111.465],[3.542,116.801],[60.145,111.567],[59.397,-20.159],[43.879,-71.319],[-11.171,-110.92],[-54.901,-91.661]],"c":true},"ix":2},"nm":"Path 2","mn":"ADBE Vector Shape - Group","hd":false},{"ty":"fl","c":{"a":0,"k":[0.46,0.46,0.46,1],"ix":4},"o":{"a":0,"k":100,"ix":5},"r":1,"bm":0,"nm":"Fill 1","mn":"ADBE Vector Graphic - Fill","hd":false},{"ty":"tr","p":{"a":0,"k":[66.349,117.051],"ix":2},"a":{"a":0,"k":[0,0],"ix":1},"s":{"a":0,"k":[100,100],"ix":3},"r":{"a":0,"k":0,"ix":6},"o":{"a":0,"k":100,"ix":7},"sk":{"a":0,"k":0,"ix":4},"sa":{"a":0,"k":0,"ix":5},"nm":"Transform"}],"nm":"Group 1","np":2,"cix":2,"bm":0,"ix":1,"mn":"ADBE Vector Group","hd":false}],"ip":0,"op":111,"st":0,"bm":0},{"ddd":0,"ind":12,"ty":4,"nm":"Body_shadow","parent":11,"sr":1,"ks":{"o":{"a":0,"k":100,"ix":11},"r":{"a":0,"k":0,"ix":10},"p":{"a":0,"k":[63.247,48.639,0],"ix":2},"a":{"a":0,"k":[60.531,83.131,0],"ix":1},"s":{"a":0,"k":[100,100,100],"ix":6}},"ao":0,"shapes":[{"ty":"gr","it":[{"ind":0,"ty":"sh","ix":1,"ks":{"a":0,"k":{"i":[[30.04,-2.015],[-26.114,36.04],[-7.808,-9.48]],"o":[[-20.076,1.348],[23.247,-32.083],[8.364,10.157]],"v":[[-4.963,79.19],[-42.44,-27.263],[36.943,-4.579]],"c":true},"ix":2},"nm":"Path 1","mn":"ADBE Vector Shape - Group","hd":false},{"ty":"fl","c":{"a":0,"k":[0.63,0.63,0.63,1],"ix":4},"o":{"a":0,"k":100,"ix":5},"r":1,"bm":0,"nm":"Fill 1","mn":"ADBE Vector Graphic - Fill","hd":false},{"ty":"tr","p":{"a":0,"k":[59.757,80.789],"ix":2},"a":{"a":0,"k":[0,0],"ix":1},"s":{"a":0,"k":[100,100],"ix":3},"r":{"a":0,"k":0,"ix":6},"o":{"a":0,"k":100,"ix":7},"sk":{"a":0,"k":0,"ix":4},"sa":{"a":0,"k":0,"ix":5},"nm":"Transform"}],"nm":"Group 1","np":2,"cix":2,"bm":0,"ix":1,"mn":"ADBE Vector Group","hd":false}],"ip":0,"op":111,"st":0,"bm":0},{"ddd":0,"ind":13,"ty":4,"nm":"Body_skin","parent":11,"sr":1,"ks":{"o":{"a":0,"k":100,"ix":11},"r":{"a":0,"k":0,"ix":10},"p":{"a":0,"k":[63.247,48.639,0],"ix":2},"a":{"a":0,"k":[60.531,83.131,0],"ix":1},"s":{"a":0,"k":[100,100,100],"ix":6}},"ao":0,"shapes":[{"ty":"gr","it":[{"ind":0,"ty":"sh","ix":1,"ks":{"a":0,"k":{"i":[[30.04,-2.015],[13.796,15.256],[-4.406,14.132],[-7.203,12.907],[-3.772,-4.015],[-7.808,-9.48],[-4.913,-12.135]],"o":[[-20.076,1.348],[-1.174,-21.791],[2.498,-8.014],[11.252,-20.163],[8.398,8.941],[8.364,10.157],[-11.208,24.779]],"v":[[-4.963,79.19],[-55.937,52.207],[-55.101,-7.966],[-34.895,-54.289],[15.609,-36.777],[40.721,-9.868],[59.507,23.351]],"c":true},"ix":2},"nm":"Path 1","mn":"ADBE Vector Shape - Group","hd":false},{"ty":"fl","c":{"a":0,"k":[0.67,0.67,0.67,1],"ix":4},"o":{"a":0,"k":100,"ix":5},"r":1,"bm":0,"nm":"Fill 1","mn":"ADBE Vector Graphic - Fill","hd":false},{"ty":"tr","p":{"a":0,"k":[59.757,80.789],"ix":2},"a":{"a":0,"k":[0,0],"ix":1},"s":{"a":0,"k":[100,100],"ix":3},"r":{"a":0,"k":0,"ix":6},"o":{"a":0,"k":100,"ix":7},"sk":{"a":0,"k":0,"ix":4},"sa":{"a":0,"k":0,"ix":5},"nm":"Transform"}],"nm":"Group 1","np":2,"cix":2,"bm":0,"ix":1,"mn":"ADBE Vector Group","hd":false}],"ip":0,"op":111,"st":0,"bm":0},{"ddd":0,"ind":14,"ty":4,"nm":"Neck","parent":11,"sr":1,"ks":{"o":{"a":0,"k":100,"ix":11},"r":{"a":0,"k":0,"ix":10},"p":{"a":0,"k":[50.795,5.769,0],"ix":2},"a":{"a":0,"k":[31.947,82.989,0],"ix":1},"s":{"a":0,"k":[100,100,100],"ix":6}},"ao":0,"shapes":[{"ty":"gr","it":[{"ind":0,"ty":"sh","ix":1,"ks":{"a":0,"k":{"i":[[-0.98,-3.08],[-4.53,-2.981],[-5.74,-1.59],[-1.19,-0.301],[-0.26,4.22],[1.03,0.239],[3.81,10.101],[0.32,-1.731],[0.03,-0.359]],"o":[[1.47,4.689],[4.81,3.16],[1.18,0.33],[0.93,-4.2],[-1.04,-0.169],[-12.13,-2.851],[-1.83,0.851],[-0.08,0.4],[-0.23,3.181]],"v":[[-14.99,-2.115],[-5.46,9.736],[10.84,16.275],[14.4,17.215],[16.28,4.574],[13.18,3.965],[-12.92,-17.215],[-15.89,-12.764],[-16.05,-11.626]],"c":true},"ix":2},"nm":"Path 1","mn":"ADBE Vector Shape - Group","hd":false},{"ty":"fl","c":{"a":0,"k":[0.63,0.63,0.63,1],"ix":4},"o":{"a":0,"k":100,"ix":5},"r":1,"bm":0,"nm":"Fill 1","mn":"ADBE Vector Graphic - Fill","hd":false},{"ty":"tr","p":{"a":0,"k":[51.344,46.925],"ix":2},"a":{"a":0,"k":[0,0],"ix":1},"s":{"a":0,"k":[100,100],"ix":3},"r":{"a":0,"k":0,"ix":6},"o":{"a":0,"k":100,"ix":7},"sk":{"a":0,"k":0,"ix":4},"sa":{"a":0,"k":0,"ix":5},"nm":"Transform"}],"nm":"Group 2","np":2,"cix":2,"bm":0,"ix":1,"mn":"ADBE Vector Group","hd":false},{"ty":"gr","it":[{"ind":0,"ty":"sh","ix":1,"ks":{"a":0,"k":{"i":[[-15.79,0.29],[-0.61,2.25],[-1.929,8.72],[-0.26,4.22],[0.219,2.67],[5.42,7.74],[10.679,0.87],[4.5,-3.71],[0.569,-0.61],[0.77,-1.27],[-0.589,-4.63],[0.188,-7.966],[0.535,-4.031]],"o":[[10.19,-0.181],[2.27,-8.32],[0.931,-4.2],[0.17,-2.67],[-0.79,-9.32],[-6.02,-8.59],[-5.881,-0.48],[-0.64,0.53],[-0.98,1.05],[-2.52,4.19],[0.991,7.773],[-0.194,8.256],[-2.24,16.58]],"v":[[-3.625,58.895],[23.58,34.377],[30.729,8.707],[32.61,-3.933],[32.55,-11.943],[23.019,-38.123],[-2.93,-54.703],[-19.461,-49.923],[-21.28,-48.203],[-23.91,-45.553],[-26.251,-30.623],[-24.525,-6.764],[-35.035,32.865]],"c":true},"ix":2},"nm":"Path 1","mn":"ADBE Vector Shape - Group","hd":false},{"ty":"fl","c":{"a":0,"k":[0.67,0.67,0.67,1],"ix":4},"o":{"a":0,"k":100,"ix":5},"r":1,"bm":0,"nm":"Fill 1","mn":"ADBE Vector Graphic - Fill","hd":false},{"ty":"tr","p":{"a":0,"k":[35.014,55.433],"ix":2},"a":{"a":0,"k":[0,0],"ix":1},"s":{"a":0,"k":[100,100],"ix":3},"r":{"a":0,"k":0,"ix":6},"o":{"a":0,"k":100,"ix":7},"sk":{"a":0,"k":0,"ix":4},"sa":{"a":0,"k":0,"ix":5},"nm":"Transform"}],"nm":"Group 3","np":2,"cix":2,"bm":0,"ix":2,"mn":"ADBE Vector Group","hd":false}],"ip":0,"op":111,"st":0,"bm":0},{"ddd":0,"ind":15,"ty":4,"nm":"Thigh","parent":2,"sr":1,"ks":{"o":{"a":0,"k":100,"ix":11},"r":{"a":1,"k":[{"i":{"x":[0.667],"y":[1]},"o":{"x":[0.333],"y":[0]},"t":1,"s":[-61]},{"i":{"x":[0.667],"y":[1]},"o":{"x":[0.333],"y":[0]},"t":27.009,"s":[-19]},{"i":{"x":[0.667],"y":[1]},"o":{"x":[0.333],"y":[0]},"t":37.991,"s":[-19]},{"t":64,"s":[-61]}],"ix":10},"p":{"a":0,"k":[65.653,50.607,0],"ix":2},"a":{"a":0,"k":[58.367,59.062,0],"ix":1},"s":{"a":0,"k":[100,100,100],"ix":6}},"ao":0,"shapes":[{"ty":"gr","it":[{"ind":0,"ty":"sh","ix":1,"ks":{"a":1,"k":[{"i":{"x":0.667,"y":1},"o":{"x":0.333,"y":0},"t":1,"s":[{"i":[[7.449,-21.497],[5.625,35.037],[-3.102,37.831],[-34.046,0.676],[-9.964,-10.786],[3.469,-26.667]],"o":[[-9.382,27.076],[-3.681,-22.924],[2.341,-28.554],[14.807,-0.294],[19.479,21.088],[-7.591,58.348]],"v":[[13.541,110.31],[-44.373,97.303],[-58.239,-76.494],[-2.041,-131.84],[37.595,-114.389],[54.065,-44.953]],"c":true}]},{"i":{"x":0.667,"y":1},"o":{"x":0.333,"y":0},"t":27.009,"s":[{"i":[[8.2,-21.221],[5.625,35.036],[-3.102,37.831],[-34.046,0.676],[-9.964,-10.786],[3.469,-26.667]],"o":[[-8.198,21.217],[-3.681,-22.924],[2.341,-28.554],[14.807,-0.294],[19.479,21.088],[-7.591,58.348]],"v":[[17.62,98.53],[-39.674,85.773],[-58.239,-76.494],[-2.041,-131.84],[37.595,-114.389],[54.065,-44.953]],"c":true}]},{"i":{"x":0.667,"y":1},"o":{"x":0.333,"y":0},"t":37.991,"s":[{"i":[[8.2,-21.221],[5.625,35.036],[-3.102,37.831],[-34.046,0.676],[-9.964,-10.786],[3.469,-26.667]],"o":[[-8.198,21.217],[-3.681,-22.924],[2.341,-28.554],[14.807,-0.294],[19.479,21.088],[-7.591,58.348]],"v":[[17.62,98.53],[-39.674,85.773],[-58.239,-76.494],[-2.041,-131.84],[37.595,-114.389],[54.065,-44.953]],"c":true}]},{"t":64,"s":[{"i":[[7.449,-21.497],[5.625,35.037],[-3.102,37.831],[-34.046,0.676],[-9.964,-10.786],[3.469,-26.667]],"o":[[-9.382,27.076],[-3.681,-22.924],[2.341,-28.554],[14.807,-0.294],[19.479,21.088],[-7.591,58.348]],"v":[[13.541,110.31],[-44.373,97.303],[-58.239,-76.494],[-2.041,-131.84],[37.595,-114.389],[54.065,-44.953]],"c":true}]}],"ix":2},"nm":"Path 1","mn":"ADBE Vector Shape - Group","hd":false},{"ty":"fl","c":{"a":0,"k":[0.45,0.45,0.45,1],"ix":4},"o":{"a":0,"k":100,"ix":5},"r":1,"bm":0,"nm":"Fill 1","mn":"ADBE Vector Graphic - Fill","hd":false},{"ty":"tr","p":{"a":0,"k":[60.338,134.587],"ix":2},"a":{"a":0,"k":[0,0],"ix":1},"s":{"a":0,"k":[100,100],"ix":3},"r":{"a":0,"k":0,"ix":6},"o":{"a":0,"k":100,"ix":7},"sk":{"a":0,"k":0,"ix":4},"sa":{"a":0,"k":0,"ix":5},"nm":"Transform"}],"nm":"Group 2","np":2,"cix":2,"bm":0,"ix":1,"mn":"ADBE Vector Group","hd":false}],"ip":0,"op":111,"st":0,"bm":0},{"ddd":0,"ind":16,"ty":4,"nm":"Foot","parent":18,"sr":1,"ks":{"o":{"a":0,"k":100,"ix":11},"r":{"a":0,"k":-1,"ix":10},"p":{"a":0,"k":[38.319,-48.631,0],"ix":2},"a":{"a":0,"k":[30.076,20.511,0],"ix":1},"s":{"a":0,"k":[111.111,111.111,100],"ix":6}},"ao":0,"shapes":[{"ty":"gr","it":[{"ind":0,"ty":"sh","ix":1,"ks":{"a":0,"k":{"i":[[-2.299,1.431],[-7.699,0.225],[-4.091,-0.103],[-0.904,-0.098],[-3.158,0.441],[-3.079,1.106],[-0.403,0.083],[-0.107,-0.508],[0.682,-2.765],[1.046,-0.364],[12.513,-0.015],[7.604,0.393],[6.471,-0.37],[2.506,3.24]],"o":[[0.49,-0.305],[3.245,-0.102],[4.978,0.132],[2.948,0.304],[3.231,-0.45],[0.106,-0.038],[0.446,-0.092],[0.392,2.155],[-0.266,1.088],[-12.195,4.208],[-7.347,0.008],[0,0],[-24.359,1.41],[-0.42,-0.618]],"v":[[-60.884,-7.602],[-28.965,-5.561],[-18.28,-5.652],[12.082,-0.876],[50.251,-0.706],[59.845,-2.857],[61.853,-7.404],[62.94,-6.891],[62.422,-0.68],[60.331,1.646],[23.396,7.03],[0.994,6.262],[-24.299,6.389],[-62.72,1.29]],"c":true},"ix":2},"nm":"Path 1","mn":"ADBE Vector Shape - Group","hd":false},{"ty":"fl","c":{"a":0,"k":[0.45,0.45,0.45,1],"ix":4},"o":{"a":0,"k":100,"ix":5},"r":1,"bm":0,"nm":"Fill 1","mn":"ADBE Vector Graphic - Fill","hd":false},{"ty":"tr","p":{"a":0,"k":[63.582,60.972],"ix":2},"a":{"a":0,"k":[0,0],"ix":1},"s":{"a":0,"k":[100,100],"ix":3},"r":{"a":0,"k":0,"ix":6},"o":{"a":0,"k":100,"ix":7},"sk":{"a":0,"k":0,"ix":4},"sa":{"a":0,"k":0,"ix":5},"nm":"Transform"}],"nm":"Group 1","np":2,"cix":2,"bm":0,"ix":1,"mn":"ADBE Vector Group","hd":false},{"ty":"gr","it":[{"ind":0,"ty":"sh","ix":1,"ks":{"a":1,"k":[{"i":{"x":0.667,"y":1},"o":{"x":0.333,"y":0},"t":1,"s":[{"i":[[0.268,1.878],[0.072,2.305],[-0.486,4.627],[-0.538,2.952],[-1.421,1.51],[-1.491,-0.792],[-2.405,-0.478],[-0.151,1.89],[-1.191,2.132],[-0.459,-1.244],[-12.969,-2.959],[-2.4,-3.07],[2.129,-4.84],[10.948,-0.804],[2.519,0.131],[2.291,-0.491],[5.445,-0.167],[2.424,0.697]],"o":[[-0.267,-1.877],[-0.072,-2.303],[0.485,-4.626],[0.538,-2.95],[1.421,-1.511],[1.492,0.793],[21.355,4.242],[0.151,-1.892],[1.192,-2.134],[0.457,1.242],[9.034,2.062],[2.4,3.069],[-3.345,7.611],[-22.84,1.678],[-2.519,-0.131],[-2.291,0.489],[-5.444,0.169],[-3.721,-1.074]],"v":[[-61.171,21.547],[-60.126,12.912],[-57.195,-5.469],[-53.795,-17.521],[-51.077,-24.521],[-46.654,-23.82],[-39.008,-13.785],[-12.237,-23.563],[-8.301,-30.091],[0.76,-21.777],[39.244,7.777],[58.493,14.096],[61.123,22.953],[33.305,30.668],[0.299,28.443],[-17.139,27.096],[-30.908,29.196],[-59.532,26.467]],"c":true}]},{"i":{"x":0.667,"y":1},"o":{"x":0.333,"y":0},"t":27.009,"s":[{"i":[[0.268,1.878],[0.072,2.305],[-0.486,4.627],[-0.538,2.952],[-1.421,1.51],[-1.491,-0.792],[-2.405,-0.478],[-0.151,1.89],[-1.191,2.132],[-0.459,-1.244],[-12.969,-2.959],[-2.4,-3.07],[2.129,-4.84],[10.948,-0.804],[2.519,0.131],[2.291,-0.491],[5.445,-0.167],[2.424,0.697]],"o":[[-0.267,-1.877],[-0.072,-2.303],[0.485,-4.626],[0.538,-2.95],[1.421,-1.511],[1.492,0.793],[21.355,4.242],[0.151,-1.892],[1.192,-2.134],[0.457,1.242],[9.034,2.062],[2.4,3.069],[-3.345,7.611],[-22.84,1.678],[-2.519,-0.131],[-2.291,0.489],[-5.444,0.169],[-3.721,-1.074]],"v":[[-61.171,21.547],[-60.126,12.912],[-59.725,-3.747],[-57.294,-17.566],[-54.576,-24.566],[-50.154,-23.865],[-42.508,-13.83],[-20.361,-23.682],[-18.049,-30.251],[-8.988,-21.937],[39.244,7.777],[58.493,14.096],[61.123,22.953],[33.305,30.668],[0.299,28.443],[-17.139,27.096],[-30.908,29.196],[-59.532,26.467]],"c":true}]},{"i":{"x":0.667,"y":1},"o":{"x":0.333,"y":0},"t":37.991,"s":[{"i":[[0.268,1.878],[0.072,2.305],[-0.486,4.627],[-0.538,2.952],[-1.421,1.51],[-1.491,-0.792],[-2.405,-0.478],[-0.151,1.89],[-1.191,2.132],[-0.459,-1.244],[-12.969,-2.959],[-2.4,-3.07],[2.129,-4.84],[10.948,-0.804],[2.519,0.131],[2.291,-0.491],[5.445,-0.167],[2.424,0.697]],"o":[[-0.267,-1.877],[-0.072,-2.303],[0.485,-4.626],[0.538,-2.95],[1.421,-1.511],[1.492,0.793],[21.355,4.242],[0.151,-1.892],[1.192,-2.134],[0.457,1.242],[9.034,2.062],[2.4,3.069],[-3.345,7.611],[-22.84,1.678],[-2.519,-0.131],[-2.291,0.489],[-5.444,0.169],[-3.721,-1.074]],"v":[[-61.171,21.547],[-60.126,12.912],[-59.725,-3.747],[-57.294,-17.566],[-54.576,-24.566],[-50.154,-23.865],[-42.508,-13.83],[-20.361,-23.682],[-18.049,-30.251],[-8.988,-21.937],[39.244,7.777],[58.493,14.096],[61.123,22.953],[33.305,30.668],[0.299,28.443],[-17.139,27.096],[-30.908,29.196],[-59.532,26.467]],"c":true}]},{"t":64,"s":[{"i":[[0.268,1.878],[0.072,2.305],[-0.486,4.627],[-0.538,2.952],[-1.421,1.51],[-1.491,-0.792],[-2.405,-0.478],[-0.151,1.89],[-1.191,2.132],[-0.459,-1.244],[-12.969,-2.959],[-2.4,-3.07],[2.129,-4.84],[10.948,-0.804],[2.519,0.131],[2.291,-0.491],[5.445,-0.167],[2.424,0.697]],"o":[[-0.267,-1.877],[-0.072,-2.303],[0.485,-4.626],[0.538,-2.95],[1.421,-1.511],[1.492,0.793],[21.355,4.242],[0.151,-1.892],[1.192,-2.134],[0.457,1.242],[9.034,2.062],[2.4,3.069],[-3.345,7.611],[-22.84,1.678],[-2.519,-0.131],[-2.291,0.489],[-5.444,0.169],[-3.721,-1.074]],"v":[[-61.171,21.547],[-60.126,12.912],[-57.195,-5.469],[-53.795,-17.521],[-51.077,-24.521],[-46.654,-23.82],[-39.008,-13.785],[-12.237,-23.563],[-8.301,-30.091],[0.76,-21.777],[39.244,7.777],[58.493,14.096],[61.123,22.953],[33.305,30.668],[0.299,28.443],[-17.139,27.096],[-30.908,29.196],[-59.532,26.467]],"c":true}]}],"ix":2},"nm":"Path 1","mn":"ADBE Vector Shape - Group","hd":false},{"ty":"fl","c":{"a":0,"k":[0.46,0.46,0.46,1],"ix":4},"o":{"a":0,"k":100,"ix":5},"r":1,"bm":0,"nm":"Fill 1","mn":"ADBE Vector Graphic - Fill","hd":false},{"ty":"tr","p":{"a":0,"k":[64.078,33.771],"ix":2},"a":{"a":0,"k":[0,0],"ix":1},"s":{"a":0,"k":[100,100],"ix":3},"r":{"a":0,"k":0,"ix":6},"o":{"a":0,"k":100,"ix":7},"sk":{"a":0,"k":0,"ix":4},"sa":{"a":0,"k":0,"ix":5},"nm":"Transform"}],"nm":"Group 2","np":2,"cix":2,"bm":0,"ix":2,"mn":"ADBE Vector Group","hd":false}],"ip":0,"op":111,"st":0,"bm":0},{"ddd":0,"ind":17,"ty":4,"nm":"Calf","parent":16,"sr":1,"ks":{"o":{"a":0,"k":100,"ix":11},"r":{"a":1,"k":[{"i":{"x":[0.667],"y":[0.568]},"o":{"x":[0.333],"y":[0]},"t":1,"s":[28]},{"i":{"x":[0.667],"y":[1]},"o":{"x":[0.333],"y":[0.413]},"t":14.294,"s":[15]},{"i":{"x":[0.667],"y":[1]},"o":{"x":[0.333],"y":[0]},"t":27.009,"s":[2]},{"i":{"x":[0.667],"y":[1]},"o":{"x":[0.333],"y":[0]},"t":37.991,"s":[2]},{"t":64,"s":[28]}],"ix":10},"p":{"a":0,"k":[29.73,20.952,0],"ix":2},"a":{"a":0,"k":[42.095,244.161,0],"ix":1},"s":{"a":0,"k":[100,100,100],"ix":6}},"ao":0,"shapes":[{"ty":"gr","it":[{"ind":0,"ty":"sh","ix":1,"ks":{"a":0,"k":{"i":[[0.002,0.022],[-1.88,8.14],[9.403,4.279],[7.654,-2.706],[2.243,-11.508],[6.218,-21.191],[-1.582,-41.644],[-5.839,-0.006]],"o":[[-6.175,-57.977],[2.304,-9.974],[-7.39,-3.362],[-11.363,4.017],[-4.302,22.059],[-12.23,41.678],[4.623,1.559],[9.881,0.014]],"v":[[9.253,98.376],[46.03,-68.497],[30.637,-97.753],[6.895,-98.789],[-13.457,-76.062],[-37.954,-13.091],[-26.332,98.861],[-9.76,101.48]],"c":true},"ix":2},"nm":"Path 1","mn":"ADBE Vector Shape - Group","hd":false},{"ty":"fl","c":{"a":0,"k":[0.45,0.45,0.45,1],"ix":4},"o":{"a":0,"k":100,"ix":5},"r":1,"bm":0,"nm":"Fill 1","mn":"ADBE Vector Graphic - Fill","hd":false},{"ty":"tr","p":{"a":0,"k":[50.434,108.196],"ix":2},"a":{"a":0,"k":[0,0],"ix":1},"s":{"a":0,"k":[100,100],"ix":3},"r":{"a":0,"k":0,"ix":6},"o":{"a":0,"k":100,"ix":7},"sk":{"a":0,"k":0,"ix":4},"sa":{"a":0,"k":0,"ix":5},"nm":"Transform"}],"nm":"Group 2","np":2,"cix":2,"bm":0,"ix":1,"mn":"ADBE Vector Group","hd":false},{"ty":"gr","it":[{"ind":0,"ty":"sh","ix":1,"ks":{"a":0,"k":{"i":[[-4.091,-0.564],[-1.437,-0.575],[-2.018,-4.814],[0.082,-3.82],[-0.13,-5.493],[-0.38,-3.055],[0.134,-2.865],[3.177,-3.6],[3.964,-0.535],[2.816,8.835],[-0.073,4.604],[-0.226,4.719],[-0.823,5.708],[-3.509,3.486]],"o":[[1.528,0.211],[4.29,1.718],[1.434,3.42],[-0.118,5.485],[0.073,3.09],[0.352,2.83],[-0.243,5.191],[-2.88,3.265],[-7.819,1.054],[-1.391,-4.362],[0.073,-4.71],[0.276,-5.762],[0.749,-5.183],[3.25,-3.228]],"v":[[0.668,-38.165],[5.144,-36.964],[15.515,-27.201],[17.165,-16.026],[16.624,0.406],[17.367,9.602],[17.82,18.097],[12.779,31.701],[2.166,37.676],[-16.502,24.575],[-17.882,10.868],[-17.471,-3.238],[-16.623,-20.58],[-10.889,-34.6]],"c":true},"ix":2},"nm":"Path 1","mn":"ADBE Vector Shape - Group","hd":false},{"ty":"fl","c":{"a":0,"k":[0.67,0.67,0.67,1],"ix":4},"o":{"a":0,"k":100,"ix":5},"r":1,"bm":0,"nm":"Fill 1","mn":"ADBE Vector Graphic - Fill","hd":false},{"ty":"tr","p":{"a":0,"k":[41.708,223.307],"ix":2},"a":{"a":0,"k":[0,0],"ix":1},"s":{"a":0,"k":[100,100],"ix":3},"r":{"a":0,"k":0,"ix":6},"o":{"a":0,"k":100,"ix":7},"sk":{"a":0,"k":0,"ix":4},"sa":{"a":0,"k":0,"ix":5},"nm":"Transform"}],"nm":"Group 3","np":2,"cix":2,"bm":0,"ix":2,"mn":"ADBE Vector Group","hd":false}],"ip":0,"op":111,"st":0,"bm":0},{"ddd":0,"ind":18,"ty":4,"nm":"Moving Step","parent":8,"sr":1,"ks":{"o":{"a":0,"k":100,"ix":11},"r":{"a":0,"k":0,"ix":10},"p":{"a":1,"k":[{"i":{"x":0.667,"y":1},"o":{"x":0.333,"y":0},"t":1,"s":[261.955,650.651,0],"to":[0,0,0],"ti":[0,0,0]},{"i":{"x":0.667,"y":1},"o":{"x":0.333,"y":0},"t":31.633,"s":[246.4,758.994,0],"to":[0,0,0],"ti":[0,0,0]},{"i":{"x":0.667,"y":1},"o":{"x":0.333,"y":0},"t":33.367,"s":[246.4,758.994,0],"to":[0,0,0],"ti":[0,0,0]},{"t":64,"s":[261.955,650.651,0]}],"ix":2},"a":{"a":0,"k":[123.909,37.966,0],"ix":1},"s":{"a":0,"k":[100,100,100],"ix":6}},"ao":0,"shapes":[{"ty":"gr","it":[{"ind":0,"ty":"sh","ix":1,"ks":{"a":0,"k":{"i":[[0,0],[0,0],[0,0],[1.788,0.011],[0,0],[1.431,-1.26]],"o":[[0,0],[0,0],[-1.344,-0.836],[0,0],[-2.281,-0.014],[0,0]],"v":[[-82.435,2.672],[82.435,2.951],[75.434,-1.404],[70.579,-2.717],[-72.517,-2.937],[-78.394,-0.965]],"c":true},"ix":2},"nm":"Path 1","mn":"ADBE Vector Shape - Group","hd":false},{"ty":"fl","c":{"a":0,"k":[0.69,0.69,0.69,1],"ix":4},"o":{"a":0,"k":100,"ix":5},"r":1,"bm":0,"nm":"Fill 1","mn":"ADBE Vector Graphic - Fill","hd":false},{"ty":"tr","p":{"a":0,"k":[82.796,3.201],"ix":2},"a":{"a":0,"k":[0,0],"ix":1},"s":{"a":0,"k":[100,100],"ix":3},"r":{"a":0,"k":0,"ix":6},"o":{"a":0,"k":100,"ix":7},"sk":{"a":0,"k":0,"ix":4},"sa":{"a":0,"k":0,"ix":5},"nm":"Transform"}],"nm":"Group 1","np":2,"cix":2,"bm":0,"ix":1,"mn":"ADBE Vector Group","hd":false},{"ty":"gr","it":[{"ind":0,"ty":"sh","ix":1,"ks":{"a":0,"k":{"i":[[-0.094,5.342],[0,0],[0,0],[0,0],[-4.679,-0.019],[0,0]],"o":[[0,0],[0,0],[0,0],[-0.022,5.413],[0,0],[4.618,0.019]],"v":[[82.005,4.399],[82.49,-13.486],[-82.379,-14.01],[-82.468,3.573],[-74.033,13.413],[73.515,13.991]],"c":true},"ix":2},"nm":"Path 1","mn":"ADBE Vector Shape - Group","hd":false},{"ty":"fl","c":{"a":0,"k":[0.63,0.63,0.63,1],"ix":4},"o":{"a":0,"k":100,"ix":5},"r":1,"bm":0,"nm":"Fill 1","mn":"ADBE Vector Graphic - Fill","hd":false},{"ty":"tr","p":{"a":0,"k":[82.74,19.588],"ix":2},"a":{"a":0,"k":[0,0],"ix":1},"s":{"a":0,"k":[100,100],"ix":3},"r":{"a":0,"k":0,"ix":6},"o":{"a":0,"k":100,"ix":7},"sk":{"a":0,"k":0,"ix":4},"sa":{"a":0,"k":0,"ix":5},"nm":"Transform"}],"nm":"Group 2","np":2,"cix":2,"bm":0,"ix":2,"mn":"ADBE Vector Group","hd":false},{"ty":"gr","it":[{"ind":0,"ty":"sh","ix":1,"ks":{"a":0,"k":{"i":[[0,0],[0,0],[0,0],[-4.571,-1.317],[0,0]],"o":[[0,0],[0,0],[0.059,4.951],[0,0],[0,0]],"v":[[98.426,-28.045],[-99.098,-28.045],[-98.957,-13.954],[-91.138,-3.369],[99.098,28.045]],"c":true},"ix":2},"nm":"Path 1","mn":"ADBE Vector Shape - Group","hd":false},{"ty":"fl","c":{"a":0,"k":[0.61,0.61,0.61,1],"ix":4},"o":{"a":0,"k":100,"ix":5},"r":1,"bm":0,"nm":"Fill 1","mn":"ADBE Vector Graphic - Fill","hd":false},{"ty":"tr","p":{"a":0,"k":[148.448,47.624],"ix":2},"a":{"a":0,"k":[0,0],"ix":1},"s":{"a":0,"k":[100,100],"ix":3},"r":{"a":0,"k":0,"ix":6},"o":{"a":0,"k":100,"ix":7},"sk":{"a":0,"k":0,"ix":4},"sa":{"a":0,"k":0,"ix":5},"nm":"Transform"}],"nm":"Group 3","np":2,"cix":2,"bm":0,"ix":3,"mn":"ADBE Vector Group","hd":false}],"ip":0,"op":111,"st":0,"bm":0},{"ddd":0,"ind":19,"ty":4,"nm":"Hips","parent":2,"sr":1,"ks":{"o":{"a":0,"k":100,"ix":11},"r":{"a":0,"k":14,"ix":10},"p":{"a":0,"k":[67.541,47.844,0],"ix":2},"a":{"a":0,"k":[67.143,85.515,0],"ix":1},"s":{"a":0,"k":[100,100,100],"ix":6}},"ao":0,"shapes":[{"ty":"gr","it":[{"ind":0,"ty":"sh","ix":1,"ks":{"a":1,"k":[{"i":{"x":0.667,"y":1},"o":{"x":0.333,"y":0},"t":1,"s":[{"i":[[-1.724,4.606],[-38.538,-0.941],[-0.001,0],[-0.063,-0.966],[1.085,-21.002],[20.71,-0.641],[8.71,8.003],[1.239,17.212]],"o":[[6.177,-16.503],[9.756,0.238],[-0.422,0.069],[1.615,24.747],[-1.491,28.865],[-22.915,0.709],[-13.427,-12.338],[-2.008,-27.894]],"v":[[-44.04,-62.415],[7.648,-68.131],[58.91,-70.024],[59.444,-60.96],[65.351,31.632],[11.694,73.49],[-37.773,54.507],[-60.873,4.269]],"c":true}]},{"i":{"x":0.667,"y":1},"o":{"x":0.333,"y":0},"t":31.633,"s":[{"i":[[-1.724,4.606],[-38.538,-0.941],[-0.001,0],[-0.063,-0.966],[1.085,-21.002],[20.71,-0.641],[8.324,8.404],[0.272,17.255]],"o":[[6.177,-16.503],[9.756,0.238],[-0.422,0.069],[1.615,24.747],[-1.491,28.865],[-22.915,0.709],[-12.971,-13.095],[-0.563,-35.719]],"v":[[-44.04,-62.415],[7.648,-68.131],[58.91,-70.024],[59.444,-60.96],[65.351,31.632],[9.42,73.842],[-40.047,54.859],[-60.746,4.778]],"c":true}]},{"i":{"x":0.667,"y":1},"o":{"x":0.333,"y":0},"t":33.367,"s":[{"i":[[-1.724,4.606],[-38.538,-0.941],[-0.001,0],[-0.063,-0.966],[1.085,-21.002],[20.71,-0.641],[8.324,8.404],[0.272,17.255]],"o":[[6.177,-16.503],[9.756,0.238],[-0.422,0.069],[1.615,24.747],[-1.491,28.865],[-22.915,0.709],[-12.971,-13.095],[-0.563,-35.719]],"v":[[-44.04,-62.415],[7.648,-68.131],[58.91,-70.024],[59.444,-60.96],[65.351,31.632],[9.42,73.842],[-40.047,54.859],[-60.746,4.778]],"c":true}]},{"t":64,"s":[{"i":[[-1.724,4.606],[-38.538,-0.941],[-0.001,0],[-0.063,-0.966],[1.085,-21.002],[20.71,-0.641],[8.71,8.003],[1.239,17.212]],"o":[[6.177,-16.503],[9.756,0.238],[-0.422,0.069],[1.615,24.747],[-1.491,28.865],[-22.915,0.709],[-13.427,-12.338],[-2.008,-27.894]],"v":[[-44.04,-62.415],[7.648,-68.131],[58.91,-70.024],[59.444,-60.96],[65.351,31.632],[11.694,73.49],[-37.773,54.507],[-60.873,4.269]],"c":true}]}],"ix":2},"nm":"Path 1","mn":"ADBE Vector Shape - Group","hd":false},{"ty":"fl","c":{"a":0,"k":[0.45,0.45,0.45,1],"ix":4},"o":{"a":0,"k":100,"ix":5},"r":1,"bm":0,"nm":"Fill 1","mn":"ADBE Vector Graphic - Fill","hd":false},{"ty":"tr","p":{"a":0,"k":[61.815,71.702],"ix":2},"a":{"a":0,"k":[0,0],"ix":1},"s":{"a":0,"k":[100,100],"ix":3},"r":{"a":0,"k":0,"ix":6},"o":{"a":0,"k":100,"ix":7},"sk":{"a":0,"k":0,"ix":4},"sa":{"a":0,"k":0,"ix":5},"nm":"Transform"}],"nm":"Group 1","np":2,"cix":2,"bm":0,"ix":1,"mn":"ADBE Vector Group","hd":false}],"ip":0,"op":111,"st":0,"bm":0},{"ddd":0,"ind":20,"ty":4,"nm":"Lower_shirt","parent":19,"sr":1,"ks":{"o":{"a":0,"k":100,"ix":11},"r":{"a":0,"k":0,"ix":10},"p":{"a":0,"k":[70.991,5.519,0],"ix":2},"a":{"a":0,"k":[53.933,55.029,0],"ix":1},"s":{"a":0,"k":[100,100,100],"ix":6}},"ao":0,"shapes":[{"ty":"gr","it":[{"ind":0,"ty":"sh","ix":1,"ks":{"a":0,"k":{"i":[[2.597,-15.08],[-27.416,-4.722],[-4.995,29.003],[8.157,11.283],[13.004,2.241],[10.407,-7.312]],"o":[[-4.996,29.003],[27.416,4.721],[2.626,-15.246],[-7.36,-10.18],[-13.16,-2.265],[-11.273,7.921]],"v":[[-47.536,-9.643],[-8.779,51.286],[49.907,7.322],[40.598,-33.994],[9.31,-53.742],[-27.154,-45.34]],"c":true},"ix":2},"nm":"Path 1","mn":"ADBE Vector Shape - Group","hd":false},{"ty":"fl","c":{"a":0,"k":[0.46,0.46,0.46,1],"ix":4},"o":{"a":0,"k":100,"ix":5},"r":1,"bm":0,"nm":"Fill 1","mn":"ADBE Vector Graphic - Fill","hd":false},{"ty":"tr","p":{"a":0,"k":[52.782,56.257],"ix":2},"a":{"a":0,"k":[0,0],"ix":1},"s":{"a":0,"k":[100,100],"ix":3},"r":{"a":0,"k":0,"ix":6},"o":{"a":0,"k":100,"ix":7},"sk":{"a":0,"k":0,"ix":4},"sa":{"a":0,"k":0,"ix":5},"nm":"Transform"}],"nm":"Group 1","np":2,"cix":2,"bm":0,"ix":1,"mn":"ADBE Vector Group","hd":false}],"ip":0,"op":111,"st":0,"bm":0},{"ddd":0,"ind":21,"ty":4,"nm":"Thigh_1","parent":2,"sr":1,"ks":{"o":{"a":0,"k":100,"ix":11},"r":{"a":1,"k":[{"i":{"x":[0.667],"y":[0.145]},"o":{"x":[0.333],"y":[0]},"t":1,"s":[-12]},{"i":{"x":[0.667],"y":[1]},"o":{"x":[0.333],"y":[0.349]},"t":16.605,"s":[-23.024]},{"i":{"x":[0.667],"y":[1]},"o":{"x":[0.333],"y":[0]},"t":31.633,"s":[-49]},{"i":{"x":[0.667],"y":[0.663]},"o":{"x":[0.333],"y":[0]},"t":33.367,"s":[-49]},{"i":{"x":[0.667],"y":[1]},"o":{"x":[0.333],"y":[0.74]},"t":48.973,"s":[-23.024]},{"t":64,"s":[-12]}],"ix":10},"p":{"a":0,"k":[68.939,48.61,0],"ix":2},"a":{"a":0,"k":[51.484,58.183,0],"ix":1},"s":{"a":0,"k":[100,100,100],"ix":6}},"ao":0,"shapes":[{"ty":"gr","it":[{"ind":0,"ty":"sh","ix":1,"ks":{"a":1,"k":[{"i":{"x":0.833,"y":0.833},"o":{"x":0.333,"y":0},"t":1,"s":[{"i":[[2.021,-2.778],[1.482,6.251],[-4.793,45.858],[-31.059,5.25],[-10.584,-8.514],[-0.157,-24.876]],"o":[[-19.717,27.105],[-1.397,-5.889],[2.755,-26.358],[13.508,-2.283],[20.692,16.644],[0.515,81.386]],"v":[[35.197,109.862],[-16.873,106.172],[-50.758,-65.692],[-9.635,-123.762],[29.005,-113.187],[55.004,-45.691]],"c":true}]},{"i":{"x":0.833,"y":0.833},"o":{"x":0.167,"y":0.167},"t":9.67,"s":[{"i":[[1.971,-2.811],[1.482,6.251],[-4.793,45.858],[-31.059,5.25],[-10.584,-8.514],[-0.157,-24.876]],"o":[[-19.44,27.78],[-1.397,-5.889],[2.755,-26.358],[13.508,-2.283],[20.692,16.644],[0.515,81.386]],"v":[[35.215,115.891],[-18.932,116.214],[-50.758,-65.692],[-9.635,-123.762],[29.005,-113.187],[55.004,-45.691]],"c":true}]},{"i":{"x":0.833,"y":0.833},"o":{"x":0.167,"y":0.167},"t":16.605,"s":[{"i":[[1.904,-2.856],[1.482,6.251],[-4.793,45.858],[-31.059,5.25],[-10.584,-8.514],[-0.157,-24.876]],"o":[[-19.073,28.678],[-1.397,-5.889],[2.755,-26.358],[13.508,-2.283],[20.692,16.644],[0.515,81.386]],"v":[[35.053,113.03],[-16.987,111.529],[-50.758,-65.692],[-9.635,-123.762],[29.005,-113.187],[55.004,-45.691]],"c":true}]},{"i":{"x":0.667,"y":1},"o":{"x":0.167,"y":0.167},"t":25.275,"s":[{"i":[[1.824,-2.909],[1.482,6.251],[-4.793,45.858],[-31.059,5.25],[-10.584,-8.514],[-0.157,-24.876]],"o":[[-18.632,29.753],[-1.397,-5.889],[2.755,-26.358],[13.508,-2.283],[20.692,16.644],[0.515,81.386]],"v":[[34.928,106.574],[-17.092,106.568],[-50.758,-65.692],[-9.635,-123.762],[29.005,-113.187],[55.004,-45.691]],"c":true}]},{"i":{"x":0.667,"y":1},"o":{"x":0.333,"y":0},"t":31.633,"s":[{"i":[[1.793,-2.93],[1.482,6.251],[-4.793,45.858],[-31.059,5.25],[-10.584,-8.514],[-0.157,-24.876]],"o":[[-18.464,30.165],[-1.397,-5.889],[2.755,-26.358],[13.508,-2.283],[20.692,16.644],[0.515,81.386]],"v":[[35.009,106.216],[-17.185,108.099],[-50.758,-65.692],[-9.635,-123.762],[29.005,-113.187],[55.004,-45.691]],"c":true}]},{"i":{"x":0.833,"y":0.833},"o":{"x":0.333,"y":0},"t":33.367,"s":[{"i":[[1.793,-2.93],[1.482,6.251],[-4.793,45.858],[-31.059,5.25],[-10.584,-8.514],[-0.157,-24.876]],"o":[[-18.464,30.165],[-1.397,-5.889],[2.755,-26.358],[13.508,-2.283],[20.692,16.644],[0.515,81.386]],"v":[[34.828,107.533],[-17.185,108.099],[-50.758,-65.692],[-9.635,-123.762],[29.005,-113.187],[55.004,-45.691]],"c":true}]},{"i":{"x":0.833,"y":0.833},"o":{"x":0.167,"y":0.167},"t":40.881,"s":[{"i":[[1.831,-2.905],[1.482,6.251],[-4.793,45.858],[-31.059,5.25],[-10.584,-8.514],[-0.157,-24.876]],"o":[[-18.672,29.657],[-1.397,-5.889],[2.755,-26.358],[13.508,-2.283],[20.692,16.644],[0.515,81.386]],"v":[[34.879,107.612],[-17.117,109.271],[-50.758,-65.692],[-9.635,-123.762],[29.005,-113.187],[55.004,-45.691]],"c":true}]},{"i":{"x":0.667,"y":1},"o":{"x":0.167,"y":0.167},"t":48.973,"s":[{"i":[[1.904,-2.856],[1.482,6.251],[-4.793,45.858],[-31.059,5.25],[-10.584,-8.514],[-0.157,-24.876]],"o":[[-19.073,28.678],[-1.397,-5.889],[2.755,-26.358],[13.508,-2.283],[20.692,16.644],[0.515,81.386]],"v":[[33.092,115.728],[-16.987,111.529],[-50.758,-65.692],[-9.635,-123.762],[29.005,-113.187],[55.004,-45.691]],"c":true}]},{"t":64,"s":[{"i":[[2.021,-2.778],[1.482,6.251],[-4.793,45.858],[-31.059,5.25],[-10.584,-8.514],[-0.157,-24.876]],"o":[[-19.717,27.105],[-1.397,-5.889],[2.755,-26.358],[13.508,-2.283],[20.692,16.644],[0.515,81.386]],"v":[[35.197,109.862],[-16.873,106.172],[-50.758,-65.692],[-9.635,-123.762],[29.005,-113.187],[55.004,-45.691]],"c":true}]}],"ix":2},"nm":"Path 1","mn":"ADBE Vector Shape - Group","hd":false},{"ty":"fl","c":{"a":0,"k":[0.41,0.41,0.41,1],"ix":4},"o":{"a":0,"k":100,"ix":5},"r":1,"bm":0,"nm":"Fill 1","mn":"ADBE Vector Graphic - Fill","hd":false},{"ty":"tr","p":{"a":0,"k":[52.245,126.295],"ix":2},"a":{"a":0,"k":[0,0],"ix":1},"s":{"a":0,"k":[100,100],"ix":3},"r":{"a":0,"k":0,"ix":6},"o":{"a":0,"k":100,"ix":7},"sk":{"a":0,"k":0,"ix":4},"sa":{"a":0,"k":0,"ix":5},"nm":"Transform"}],"nm":"Group 2","np":2,"cix":2,"bm":0,"ix":1,"mn":"ADBE Vector Group","hd":false}],"ip":0,"op":111,"st":0,"bm":0},{"ddd":0,"ind":22,"ty":4,"nm":"Foot_1","parent":24,"sr":1,"ks":{"o":{"a":0,"k":100,"ix":11},"r":{"a":0,"k":-1,"ix":10},"p":{"a":0,"k":[51.049,-40.073,0],"ix":2},"a":{"a":0,"k":[29.759,21.725,0],"ix":1},"s":{"a":0,"k":[111.111,111.111,100],"ix":6}},"ao":0,"shapes":[{"ty":"gr","it":[{"ind":0,"ty":"sh","ix":1,"ks":{"a":0,"k":{"i":[[-0.008,0.244],[-0.465,0.942],[-0.299,0.108],[-0.088,-0.008],[-7.118,0.208],[-3.783,-0.095],[-3.265,-0.73],[-0.307,-0.072],[-0.625,-0.153],[-1.717,-0.324],[-0.15,-0.027],[-0.159,-0.027],[-0.273,-0.036],[-1.364,-0.17],[-0.115,-0.009],[-0.106,-0.009],[-0.915,-0.099],[-2.735,-0.173],[-3.017,-0.05],[-3.08,0.142],[-2.921,0.407],[-2.846,1.021],[-0.068,0.079],[-0.014,0.12],[-0.403,0.954],[-0.373,0.076],[-0.099,-0.469],[0.631,-2.556],[0.967,-0.337],[11.57,-0.012],[7.031,0.363],[0,0],[5.982,-0.342],[2.318,2.996],[-0.078,0.762]],"o":[[0.113,-1.722],[0.176,-0.372],[0.502,-0.182],[14.564,2.394],[3,-0.094],[4.603,0.122],[0.316,0.072],[0.643,0.154],[1.707,0.406],[0.149,0.018],[0.149,0.027],[0.264,0.045],[1.117,0.162],[0.105,0.009],[0.106,0.017],[0.844,0.107],[2.726,0.281],[3.01,0.192],[3.083,0.052],[2.945,-0.134],[2.986,-0.417],[0.098,-0.035],[0.079,-0.091],[0.115,-1.017],[0.156,-0.369],[0.411,-0.085],[0.362,1.993],[-0.245,1.006],[-11.276,3.891],[-6.792,0.008],[0,0],[-8.447,-0.435],[-22.523,1.303],[-0.388,-0.572],[-0.07,-0.19]],"v":[[-58.55,-1.445],[-57.068,-6.348],[-56.295,-7.029],[-55.186,-7.131],[-26.782,-5.143],[-16.902,-5.227],[-5.47,-3.745],[-4.529,-3.537],[-2.636,-3.087],[2.425,-1.96],[2.873,-1.887],[3.331,-1.807],[4.132,-1.68],[7.863,-1.178],[8.197,-1.142],[8.523,-1.105],[11.171,-0.81],[19.363,-0.128],[28.405,0.243],[37.654,0.126],[46.464,-0.652],[55.334,-2.641],[55.602,-2.795],[55.712,-3.135],[56.244,-6.208],[57.191,-6.844],[58.196,-6.372],[57.716,-0.629],[55.783,1.521],[21.632,6.499],[0.919,5.79],[-0.788,5.702],[-22.467,5.908],[-57.993,1.193],[-58.461,-0.793]],"c":true},"ix":2},"nm":"Path 1","mn":"ADBE Vector Shape - Group","hd":false},{"ty":"fl","c":{"a":0,"k":[0.36,0.36,0.36,1],"ix":4},"o":{"a":0,"k":100,"ix":5},"r":1,"bm":0,"nm":"Fill 1","mn":"ADBE Vector Graphic - Fill","hd":false},{"ty":"tr","p":{"a":0,"k":[58.808,55.308],"ix":2},"a":{"a":0,"k":[0,0],"ix":1},"s":{"a":0,"k":[100,100],"ix":3},"r":{"a":0,"k":0,"ix":6},"o":{"a":0,"k":100,"ix":7},"sk":{"a":0,"k":0,"ix":4},"sa":{"a":0,"k":0,"ix":5},"nm":"Transform"}],"nm":"Group 1","np":2,"cix":2,"bm":0,"ix":1,"mn":"ADBE Vector Group","hd":false},{"ty":"gr","it":[{"ind":0,"ty":"sh","ix":1,"ks":{"a":1,"k":[{"i":{"x":0.667,"y":1},"o":{"x":0.333,"y":0},"t":1,"s":[{"i":[[0.248,1.736],[0.065,2.13],[-1.403,2.393],[-1.782,0.709],[-5.575,-0.611],[-2.819,1.189],[-2.176,0.604],[-0.424,-1.149],[-11.992,-2.737],[-2.22,-2.839],[1.967,-4.476],[10.124,-0.744],[2.33,0.121],[2.119,-0.454],[5.034,-0.154],[2.241,0.645]],"o":[[-0.248,-1.735],[-0.067,-2.13],[1.696,-2.894],[8.808,-3.504],[2.254,0.247],[6.193,-2.613],[4.373,-1.213],[0.423,1.15],[8.352,1.906],[2.219,2.838],[-3.094,7.036],[-21.118,1.55],[-2.329,-0.122],[-2.117,0.453],[-5.034,0.156],[-3.44,-0.993]],"v":[[-56.56,19.923],[-55.592,11.94],[-50.488,-15.448],[-46.204,-23.141],[-35.045,-13.214],[-18.444,-13.8],[-12.39,-25.419],[-2.923,-15.714],[36.287,7.192],[54.085,13.033],[56.517,21.224],[30.794,28.357],[0.276,26.299],[-15.848,25.053],[-28.577,26.996],[-55.044,24.472]],"c":true}]},{"i":{"x":0.667,"y":1},"o":{"x":0.333,"y":0},"t":31.633,"s":[{"i":[[0.248,1.736],[0.065,2.13],[-1.403,2.393],[-1.782,0.709],[-5.575,-0.611],[-2.819,1.189],[-3.522,-0.101],[-1.38,-1.602],[-11.992,-2.737],[-2.22,-2.839],[1.967,-4.476],[10.124,-0.744],[2.33,0.121],[2.119,-0.454],[5.034,-0.154],[2.241,0.645]],"o":[[-0.248,-1.735],[-0.067,-2.13],[1.696,-2.894],[8.808,-3.504],[2.254,0.247],[6.193,-2.613],[4.537,0.13],[0.8,0.928],[8.352,1.906],[2.219,2.838],[-3.094,7.036],[-21.118,1.55],[-2.329,-0.122],[-2.117,0.453],[-5.034,0.156],[-3.44,-0.993]],"v":[[-56.56,19.923],[-55.592,11.94],[-48.989,-15.402],[-44.705,-23.094],[-33.545,-13.167],[-14.703,-13.235],[-6.165,-23.935],[2.048,-14.002],[36.287,7.192],[54.085,13.033],[56.517,21.224],[30.794,28.357],[0.276,26.299],[-15.848,25.053],[-28.577,26.996],[-55.044,24.472]],"c":true}]},{"i":{"x":0.667,"y":1},"o":{"x":0.333,"y":0},"t":33.367,"s":[{"i":[[0.248,1.736],[0.065,2.13],[-1.403,2.393],[-1.782,0.709],[-5.575,-0.611],[-2.819,1.189],[-3.522,-0.101],[-1.38,-1.602],[-11.992,-2.737],[-2.22,-2.839],[1.967,-4.476],[10.124,-0.744],[2.33,0.121],[2.119,-0.454],[5.034,-0.154],[2.241,0.645]],"o":[[-0.248,-1.735],[-0.067,-2.13],[1.696,-2.894],[8.808,-3.504],[2.254,0.247],[6.193,-2.613],[4.537,0.13],[0.8,0.928],[8.352,1.906],[2.219,2.838],[-3.094,7.036],[-21.118,1.55],[-2.329,-0.122],[-2.117,0.453],[-5.034,0.156],[-3.44,-0.993]],"v":[[-56.56,19.923],[-55.592,11.94],[-48.989,-15.402],[-44.705,-23.094],[-33.545,-13.167],[-14.703,-13.235],[-6.165,-23.935],[2.048,-14.002],[36.287,7.192],[54.085,13.033],[56.517,21.224],[30.794,28.357],[0.276,26.299],[-15.848,25.053],[-28.577,26.996],[-55.044,24.472]],"c":true}]},{"t":64,"s":[{"i":[[0.248,1.736],[0.065,2.13],[-1.403,2.393],[-1.782,0.709],[-5.575,-0.611],[-2.819,1.189],[-2.176,0.604],[-0.424,-1.149],[-11.992,-2.737],[-2.22,-2.839],[1.967,-4.476],[10.124,-0.744],[2.33,0.121],[2.119,-0.454],[5.034,-0.154],[2.241,0.645]],"o":[[-0.248,-1.735],[-0.067,-2.13],[1.696,-2.894],[8.808,-3.504],[2.254,0.247],[6.193,-2.613],[4.373,-1.213],[0.423,1.15],[8.352,1.906],[2.219,2.838],[-3.094,7.036],[-21.118,1.55],[-2.329,-0.122],[-2.117,0.453],[-5.034,0.156],[-3.44,-0.993]],"v":[[-56.56,19.923],[-55.592,11.94],[-50.488,-15.448],[-46.204,-23.141],[-35.045,-13.214],[-18.444,-13.8],[-12.39,-25.419],[-2.923,-15.714],[36.287,7.192],[54.085,13.033],[56.517,21.224],[30.794,28.357],[0.276,26.299],[-15.848,25.053],[-28.577,26.996],[-55.044,24.472]],"c":true}]}],"ix":2},"nm":"Path 1","mn":"ADBE Vector Shape - Group","hd":false},{"ty":"fl","c":{"a":0,"k":[0.42,0.42,0.42,1],"ix":4},"o":{"a":0,"k":100,"ix":5},"r":1,"bm":0,"nm":"Fill 1","mn":"ADBE Vector Graphic - Fill","hd":false},{"ty":"tr","p":{"a":0,"k":[59.267,30.157],"ix":2},"a":{"a":0,"k":[0,0],"ix":1},"s":{"a":0,"k":[100,100],"ix":3},"r":{"a":0,"k":0,"ix":6},"o":{"a":0,"k":100,"ix":7},"sk":{"a":0,"k":0,"ix":4},"sa":{"a":0,"k":0,"ix":5},"nm":"Transform"}],"nm":"Group 2","np":2,"cix":2,"bm":0,"ix":2,"mn":"ADBE Vector Group","hd":false}],"ip":0,"op":111,"st":0,"bm":0},{"ddd":0,"ind":23,"ty":4,"nm":"Calf_1","parent":22,"sr":1,"ks":{"o":{"a":0,"k":100,"ix":11},"r":{"a":1,"k":[{"i":{"x":[0.667],"y":[0.2]},"o":{"x":[0.333],"y":[0]},"t":1,"s":[-3]},{"i":{"x":[0.667],"y":[1]},"o":{"x":[0.333],"y":[0.36]},"t":16.605,"s":[4]},{"i":{"x":[0.667],"y":[1]},"o":{"x":[0.333],"y":[0]},"t":31.633,"s":[19]},{"i":{"x":[0.667],"y":[0.604]},"o":{"x":[0.333],"y":[0]},"t":33.367,"s":[19]},{"i":{"x":[0.667],"y":[1]},"o":{"x":[0.333],"y":[0.817]},"t":48.973,"s":[4]},{"t":64,"s":[-3]}],"ix":10},"p":{"a":0,"k":[31.93,17.489,0],"ix":2},"a":{"a":0,"k":[34.597,217.813,0],"ix":1},"s":{"a":0,"k":[100,100,100],"ix":6}},"ao":0,"shapes":[{"ty":"gr","it":[{"ind":0,"ty":"sh","ix":1,"ks":{"a":0,"k":{"i":[[0.001,0.021],[-1.132,10.022],[3.203,5.519],[6.602,1.94],[3.607,-14.344],[6.921,-19.612],[0.62,-39.241],[-5.489,-0.303]],"o":[[-3.183,-63.392],[0.715,-6.324],[-3.518,-6.061],[-14.854,-4.362],[-5.161,20.526],[-13.609,38.573],[4.269,1.699],[9.292,0.513]],"v":[[5.559,93.329],[47.296,-60.24],[42.313,-79.611],[25.33,-91.437],[-7.227,-70.925],[-33.191,-13.881],[-27.93,91.983],[-12.479,95.286]],"c":true},"ix":2},"nm":"Path 1","mn":"ADBE Vector Shape - Group","hd":false},{"ty":"fl","c":{"a":0,"k":[0.41,0.41,0.41,1],"ix":4},"o":{"a":0,"k":100,"ix":5},"r":1,"bm":0,"nm":"Fill 1","mn":"ADBE Vector Graphic - Fill","hd":false},{"ty":"tr","p":{"a":0,"k":[47.05,96.049],"ix":2},"a":{"a":0,"k":[0,0],"ix":1},"s":{"a":0,"k":[100,100],"ix":3},"r":{"a":0,"k":0,"ix":6},"o":{"a":0,"k":100,"ix":7},"sk":{"a":0,"k":0,"ix":4},"sa":{"a":0,"k":0,"ix":5},"nm":"Transform"}],"nm":"Group 2","np":2,"cix":2,"bm":0,"ix":1,"mn":"ADBE Vector Group","hd":false},{"ty":"gr","it":[{"ind":0,"ty":"sh","ix":1,"ks":{"a":0,"k":{"i":[[-3.747,-0.7],[-1.297,-0.549],[-1.611,-3.996],[0.346,-5.302],[0.032,-3.479],[0.405,-3.298],[3.121,-2.709],[3.687,-0.193],[2.138,7.283],[-0.308,3.702],[-0.455,3.786],[-1.059,4.547],[-3.422,2.595]],"o":[[1.4,0.262],[3.87,1.641],[2.054,5.094],[-0.226,3.473],[-0.031,3.317],[-0.496,4.166],[-2.829,2.456],[-7.273,0.38],[-1.056,-3.595],[0.314,-3.788],[0.556,-4.622],[0.962,-4.129],[3.168,-2.405]],"v":[[2.501,-30.42],[6.57,-29.184],[15.633,-20.701],[15.892,-4.521],[15.503,5.91],[15.39,15.913],[10.025,26.565],[-0.084,30.74],[-16.631,19.071],[-17.188,7.951],[-16.07,-3.384],[-14.379,-17.297],[-8.353,-28.242]],"c":true},"ix":2},"nm":"Path 1","mn":"ADBE Vector Shape - Group","hd":false},{"ty":"fl","c":{"a":0,"k":[0.57,0.57,0.57,1],"ix":4},"o":{"a":0,"k":100,"ix":5},"r":1,"bm":0,"nm":"Fill 1","mn":"ADBE Vector Graphic - Fill","hd":false},{"ty":"tr","p":{"a":0,"k":[35.092,202.551],"ix":2},"a":{"a":0,"k":[0,0],"ix":1},"s":{"a":0,"k":[100,100],"ix":3},"r":{"a":0,"k":0,"ix":6},"o":{"a":0,"k":100,"ix":7},"sk":{"a":0,"k":0,"ix":4},"sa":{"a":0,"k":0,"ix":5},"nm":"Transform"}],"nm":"Group 4","np":2,"cix":2,"bm":0,"ix":2,"mn":"ADBE Vector Group","hd":false}],"ip":0,"op":111,"st":0,"bm":0},{"ddd":0,"ind":24,"ty":4,"nm":"Moving Step_1","parent":8,"sr":1,"ks":{"o":{"a":0,"k":100,"ix":11},"r":{"a":0,"k":0,"ix":10},"p":{"a":1,"k":[{"i":{"x":0.667,"y":1},"o":{"x":0.333,"y":0},"t":1,"s":[246.021,736.836,0],"to":[0,0,0],"ti":[0,0,0]},{"i":{"x":0.667,"y":1},"o":{"x":0.333,"y":0},"t":31.633,"s":[264.354,640.03,0],"to":[0,0,0],"ti":[0,0,0]},{"i":{"x":0.667,"y":1},"o":{"x":0.333,"y":0},"t":33.367,"s":[264.354,640.03,0],"to":[0,0,0],"ti":[0,0,0]},{"t":64,"s":[246.021,736.836,0]}],"ix":2},"a":{"a":0,"k":[123.909,37.966,0],"ix":1},"s":{"a":0,"k":[100,100,100],"ix":6}},"ao":0,"shapes":[{"ty":"gr","it":[{"ind":0,"ty":"sh","ix":1,"ks":{"a":0,"k":{"i":[[0,0],[0,0],[0,0],[1.788,0.011],[0,0],[1.431,-1.26]],"o":[[0,0],[0,0],[-1.344,-0.836],[0,0],[-2.281,-0.014],[0,0]],"v":[[-82.435,2.672],[82.435,2.951],[75.434,-1.404],[70.579,-2.717],[-72.517,-2.937],[-78.394,-0.965]],"c":true},"ix":2},"nm":"Path 1","mn":"ADBE Vector Shape - Group","hd":false},{"ty":"fl","c":{"a":0,"k":[0.67,0.67,0.67,1],"ix":4},"o":{"a":0,"k":100,"ix":5},"r":1,"bm":0,"nm":"Fill 1","mn":"ADBE Vector Graphic - Fill","hd":false},{"ty":"tr","p":{"a":0,"k":[82.796,3.201],"ix":2},"a":{"a":0,"k":[0,0],"ix":1},"s":{"a":0,"k":[100,100],"ix":3},"r":{"a":0,"k":0,"ix":6},"o":{"a":0,"k":100,"ix":7},"sk":{"a":0,"k":0,"ix":4},"sa":{"a":0,"k":0,"ix":5},"nm":"Transform"}],"nm":"Group 1","np":2,"cix":2,"bm":0,"ix":1,"mn":"ADBE Vector Group","hd":false},{"ty":"gr","it":[{"ind":0,"ty":"sh","ix":1,"ks":{"a":0,"k":{"i":[[-0.094,5.342],[0,0],[0,0],[0,0],[-4.679,-0.019],[0,0]],"o":[[0,0],[0,0],[0,0],[-0.022,5.413],[0,0],[4.618,0.019]],"v":[[82.005,4.399],[82.49,-13.486],[-82.379,-14.01],[-82.468,3.574],[-74.033,13.413],[73.515,13.992]],"c":true},"ix":2},"nm":"Path 1","mn":"ADBE Vector Shape - Group","hd":false},{"ty":"fl","c":{"a":0,"k":[0.61,0.61,0.61,1],"ix":4},"o":{"a":0,"k":100,"ix":5},"r":1,"bm":0,"nm":"Fill 1","mn":"ADBE Vector Graphic - Fill","hd":false},{"ty":"tr","p":{"a":0,"k":[82.74,19.589],"ix":2},"a":{"a":0,"k":[0,0],"ix":1},"s":{"a":0,"k":[100,100],"ix":3},"r":{"a":0,"k":0,"ix":6},"o":{"a":0,"k":100,"ix":7},"sk":{"a":0,"k":0,"ix":4},"sa":{"a":0,"k":0,"ix":5},"nm":"Transform"}],"nm":"Group 2","np":2,"cix":2,"bm":0,"ix":2,"mn":"ADBE Vector Group","hd":false},{"ty":"gr","it":[{"ind":0,"ty":"sh","ix":1,"ks":{"a":0,"k":{"i":[[0,0],[0,0],[0,0],[-4.571,-1.317],[0,0]],"o":[[0,0],[0,0],[0.059,4.951],[0,0],[0,0]],"v":[[98.426,-28.045],[-99.098,-28.045],[-98.957,-13.954],[-91.138,-3.37],[99.098,28.045]],"c":true},"ix":2},"nm":"Path 1","mn":"ADBE Vector Shape - Group","hd":false},{"ty":"fl","c":{"a":0,"k":[0.56,0.56,0.56,1],"ix":4},"o":{"a":0,"k":100,"ix":5},"r":1,"bm":0,"nm":"Fill 1","mn":"ADBE Vector Graphic - Fill","hd":false},{"ty":"tr","p":{"a":0,"k":[148.448,47.624],"ix":2},"a":{"a":0,"k":[0,0],"ix":1},"s":{"a":0,"k":[100,100],"ix":3},"r":{"a":0,"k":0,"ix":6},"o":{"a":0,"k":100,"ix":7},"sk":{"a":0,"k":0,"ix":4},"sa":{"a":0,"k":0,"ix":5},"nm":"Transform"}],"nm":"Group 3","np":2,"cix":2,"bm":0,"ix":3,"mn":"ADBE Vector Group","hd":false}],"ip":0,"op":111,"st":0,"bm":0},{"ddd":0,"ind":25,"ty":4,"nm":"Handle_1","parent":8,"sr":1,"ks":{"o":{"a":0,"k":100,"ix":11},"r":{"a":0,"k":0,"ix":10},"p":{"a":0,"k":[349.417,502.249,0],"ix":2},"a":{"a":0,"k":[278.972,322.736,0],"ix":1},"s":{"a":0,"k":[100,100,100],"ix":6}},"ao":0,"shapes":[{"ty":"gr","it":[{"ind":0,"ty":"sh","ix":1,"ks":{"a":0,"k":{"i":[[6.977,-0.598],[4.212,-0.361],[11.209,-0.961],[16.064,-1.377],[18.776,-1.609],[19.345,-1.658],[0,0],[14.012,-1.201],[8.219,-0.704],[1.246,-0.11],[13.342,-6.212],[9.768,-10.248],[5.826,-14.086],[1.366,-6.58],[-6.872,-1.565],[-1.42,6.847],[-1.381,4.107],[-0.782,1.935],[-0.144,0.368],[-0.374,0.842],[-0.516,1.064],[-2.213,3.466],[-1.137,1.58],[-0.577,0.782],[-0.722,0.876],[-2.931,2.817],[-1.542,1.321],[-0.828,0.667],[-0.303,0.24],[-2.529,1.882],[-7.483,3.3],[-1.483,0.589],[-0.64,0.247],[-1.113,0.387],[-2.285,0.626],[-4.757,0.642],[1.108,-0.149],[-4.234,0.363],[-7.83,0.671],[-11.856,1.016],[0,0],[-16.047,1.376],[-16.246,1.393],[-15.112,1.295],[-12.796,1.097],[-9.256,0.794],[-4.383,0.398],[-0.186,0.016],[-2.461,2.461],[0.139,3.114]],"o":[[-4.213,0.361],[-11.21,0.961],[-16.064,1.376],[-18.776,1.609],[-19.344,1.658],[0,0],[-14.012,1.201],[-8.219,0.704],[-1.246,0.107],[-14.661,1.29],[-12.842,5.979],[-10.555,11.071],[-2.569,6.212],[-1.324,6.385],[6.253,1.425],[0.881,-4.243],[0.665,-1.979],[0.148,-0.367],[-1.485,3.809],[0.48,-1.081],[1.793,-3.7],[1.048,-1.64],[0.567,-0.789],[-2.649,3.587],[2.586,-3.136],[1.463,-1.407],[0.808,-0.691],[0.302,-0.243],[1.654,-1.315],[6.566,-4.885],[2.056,-0.906],[0.638,-0.254],[1.1,-0.425],[2.237,-0.779],[4.63,-1.267],[-1.108,0.149],[4.216,-0.544],[7.831,-0.672],[11.857,-1.016],[0,0],[16.048,-1.376],[16.246,-1.392],[15.112,-1.295],[12.795,-1.097],[9.255,-0.793],[4.384,-0.375],[0.186,-0.017],[3.37,-0.289],[2.168,-2.168],[-0.282,-6.294]],"v":[[213.88,-68.973],[201.242,-67.89],[167.612,-65.007],[119.42,-60.877],[63.093,-56.049],[5.06,-51.075],[-48.25,-46.506],[-90.286,-42.903],[-114.945,-40.79],[-118.683,-40.469],[-160.523,-29.306],[-194.985,-4.425],[-219.312,33.533],[-225.195,52.77],[-216.463,68.146],[-201.088,59.416],[-197.713,46.878],[-195.542,41.004],[-195.092,39.905],[-195.415,40.712],[-193.921,37.495],[-187.907,26.735],[-184.628,21.904],[-182.894,19.562],[-182.317,18.901],[-174.032,9.963],[-169.521,5.87],[-167.067,3.832],[-166.16,3.109],[-166.385,3.299],[-145.23,-8.919],[-146.322,-8.454],[-144.411,-9.215],[-141.092,-10.433],[-134.307,-12.542],[-120.21,-15.389],[-123.533,-14.942],[-110.831,-16.142],[-87.339,-18.156],[-51.771,-21.204],[-8.206,-24.938],[39.937,-29.065],[88.674,-33.242],[134.01,-37.127],[172.397,-40.418],[200.165,-42.798],[213.32,-43.925],[213.88,-43.973],[222.718,-47.634],[226.38,-56.473]],"c":true},"ix":2},"nm":"Path 1","mn":"ADBE Vector Shape - Group","hd":false},{"ty":"fl","c":{"a":0,"k":[0.57,0.57,0.57,1],"ix":4},"o":{"a":0,"k":100,"ix":5},"r":1,"bm":0,"nm":"Fill 1","mn":"ADBE Vector Graphic - Fill","hd":false},{"ty":"tr","p":{"a":0,"k":[330.284,69.821],"ix":2},"a":{"a":0,"k":[0,0],"ix":1},"s":{"a":0,"k":[100,100],"ix":3},"r":{"a":0,"k":0,"ix":6},"o":{"a":0,"k":100,"ix":7},"sk":{"a":0,"k":0,"ix":4},"sa":{"a":0,"k":0,"ix":5},"nm":"Transform"}],"nm":"Group 1","np":2,"cix":2,"bm":0,"ix":1,"mn":"ADBE Vector Group","hd":false},{"ty":"gr","it":[{"ind":0,"ty":"sh","ix":1,"ks":{"a":0,"k":{"i":[[6.977,-0.598],[5.447,-0.467],[14.283,-1.224],[0,0],[22.088,-1.893],[21.292,-1.825],[17.078,-1.464],[9.757,-0.836],[17.324,-10.876],[6.494,-31.238],[0.796,-3.896],[2.08,-10.173],[3.074,-15.036],[3.806,-18.618],[4.291,-20.984],[0,0],[0,0],[4.062,-19.869],[3.428,-16.766],[0,0],[0,0],[0.176,-0.864],[-6.884,-1.568],[-1.401,6.85],[-0.725,3.546],[-2.01,9.831],[-3.01,14.723],[-3.77,18.441],[-4.23,20.687],[-4.44,21.714],[-4.404,21.54],[-4.062,19.866],[-3.475,16.995],[-2.633,12.876],[-1.5,7.335],[-0.251,1.21],[-1.805,4.948],[-0.372,0.934],[-0.098,0.398],[-0.581,1.271],[-0.9,1.782],[-2.082,3.202],[-1.076,1.479],[-0.329,0.455],[0.005,-0.006],[-0.617,0.743],[-2.712,2.634],[-1.368,1.198],[-0.754,0.624],[1.382,-1.169],[-0.396,0.288],[-0.691,0.478],[-1.674,1.024],[-3.57,1.666],[-0.773,0.345],[-2.214,0.857],[-2.026,0.67],[-3.786,0.802],[-1.86,0.292],[-0.401,0.119],[-1.437,0.153],[-1.169,0.107],[-5.499,0.471],[0,0],[-19.693,1.688],[-21.972,1.884],[-21.166,1.814],[-17.26,1.479],[-10.019,0.858],[-1.34,0.115],[0.32,7.15]],"o":[[-5.447,0.467],[-14.283,1.224],[0,0],[-22.088,1.893],[-21.292,1.825],[-17.078,1.463],[-9.757,0.836],[-20.198,1.731],[-26.966,16.929],[-0.81,3.893],[-2.08,10.173],[-3.075,15.036],[-3.807,18.618],[-4.291,20.985],[0,0],[0,0],[-4.062,19.868],[-3.428,16.766],[0,0],[0,0],[-0.177,0.864],[-1.307,6.388],[6.237,1.421],[0.725,-3.546],[2.01,-9.83],[3.011,-14.722],[3.77,-18.44],[4.23,-20.687],[4.44,-21.713],[4.404,-21.539],[4.062,-19.866],[3.475,-16.995],[2.633,-12.876],[1.5,-7.336],[0.247,-1.212],[1.071,-5.155],[0.344,-0.945],[0.152,-0.382],[-0.003,0.011],[0.83,-1.815],[1.724,-3.409],[0.998,-1.533],[0.33,-0.455],[0.809,-1.117],[0.676,-0.686],[2.414,-2.909],[1.304,-1.267],[0.736,-0.645],[0.406,-0.336],[-1.469,1.243],[0.679,-0.493],[1.615,-1.115],[3.361,-2.054],[0.768,-0.358],[2.165,-0.967],[1.99,-0.769],[3.675,-1.216],[1.843,-0.391],[0.414,-0.065],[-0.002,0.001],[1.167,-0.123],[5.496,-0.501],[0,0],[19.694,-1.688],[21.972,-1.883],[21.166,-1.814],[17.261,-1.48],[10.019,-0.859],[1.34,-0.115],[6.498,-0.557],[-0.282,-6.294]],"v":[[265.547,-322.155],[249.205,-320.754],[206.356,-317.082],[147.057,-311.999],[80.793,-306.32],[16.918,-300.845],[-34.316,-296.454],[-63.588,-293.945],[-120.442,-276.186],[-173.531,-200.388],[-175.921,-188.7],[-182.161,-158.181],[-191.384,-113.073],[-202.804,-57.219],[-215.676,5.734],[-229.071,71.246],[-242.239,135.649],[-254.426,195.254],[-264.71,245.552],[-272.344,282.887],[-276.53,303.363],[-277.06,305.956],[-268.33,321.332],[-252.953,312.602],[-250.778,301.964],[-244.749,272.473],[-235.718,228.306],[-224.407,172.985],[-211.718,110.925],[-198.399,45.784],[-185.187,-18.835],[-173.001,-78.433],[-162.576,-129.419],[-154.678,-168.047],[-150.178,-190.054],[-149.436,-193.688],[-145.148,-208.864],[-144.073,-211.682],[-143.59,-212.877],[-144.012,-211.866],[-141.466,-217.279],[-135.751,-227.204],[-132.638,-231.723],[-131.636,-233.079],[-132.308,-232.219],[-130.458,-234.511],[-122.763,-242.834],[-118.754,-246.531],[-116.519,-248.436],[-115.162,-249.557],[-113.743,-250.599],[-111.687,-252.056],[-106.751,-255.265],[-96.343,-260.852],[-94.027,-261.899],[-93.879,-261.951],[-87.872,-264.141],[-76.669,-267.174],[-71.113,-268.198],[-69.817,-268.395],[-70.97,-268.238],[-67.47,-268.611],[-50.974,-270.026],[-8.807,-273.64],[50.273,-278.704],[116.19,-284.354],[179.688,-289.796],[231.47,-294.234],[261.527,-296.81],[265.547,-297.155],[278.047,-309.655]],"c":true},"ix":2},"nm":"Path 1","mn":"ADBE Vector Shape - Group","hd":false},{"ty":"fl","c":{"a":0,"k":[0.67,0.67,0.67,1],"ix":4},"o":{"a":0,"k":100,"ix":5},"r":1,"bm":0,"nm":"Fill 1","mn":"ADBE Vector Graphic - Fill","hd":false},{"ty":"tr","p":{"a":0,"k":[278.617,323.003],"ix":2},"a":{"a":0,"k":[0,0],"ix":1},"s":{"a":0,"k":[100,100],"ix":3},"r":{"a":0,"k":0,"ix":6},"o":{"a":0,"k":100,"ix":7},"sk":{"a":0,"k":0,"ix":4},"sa":{"a":0,"k":0,"ix":5},"nm":"Transform"}],"nm":"Group 2","np":2,"cix":2,"bm":0,"ix":2,"mn":"ADBE Vector Group","hd":false}],"ip":0,"op":111,"st":0,"bm":0},{"ddd":0,"ind":26,"ty":4,"nm":"Arm_1","parent":11,"sr":1,"ks":{"o":{"a":0,"k":100,"ix":11},"r":{"a":1,"k":[{"i":{"x":[0.833],"y":[1]},"o":{"x":[0.333],"y":[0]},"t":1,"s":[-3]},{"i":{"x":[0.667],"y":[1]},"o":{"x":[0.167],"y":[0]},"t":16.605,"s":[-15]},{"i":{"x":[0.667],"y":[1]},"o":{"x":[0.333],"y":[0]},"t":31.633,"s":[-3]},{"i":{"x":[0.833],"y":[1]},"o":{"x":[0.333],"y":[0]},"t":33.367,"s":[-3]},{"i":{"x":[0.667],"y":[1]},"o":{"x":[0.167],"y":[0]},"t":48.395,"s":[-15]},{"t":64,"s":[-3]}],"ix":10},"p":{"a":1,"k":[{"i":{"x":0.667,"y":1},"o":{"x":0.333,"y":0},"t":1,"s":[52.015,40.371,0],"to":[0,0,0],"ti":[0,0,0]},{"i":{"x":0.667,"y":1},"o":{"x":0.333,"y":0},"t":16.605,"s":[53.225,45.223,0],"to":[0,0,0],"ti":[0,0,0]},{"i":{"x":0.667,"y":0.667},"o":{"x":0.333,"y":0.333},"t":31.633,"s":[52.015,40.371,0],"to":[0,0,0],"ti":[0,0,0]},{"i":{"x":0.667,"y":1},"o":{"x":0.333,"y":0},"t":33.367,"s":[52.015,40.371,0],"to":[0,0,0],"ti":[0,0,0]},{"i":{"x":0.667,"y":1},"o":{"x":0.333,"y":0},"t":48.395,"s":[53.225,45.223,0],"to":[0,0,0],"ti":[0,0,0]},{"t":64,"s":[52.015,40.371,0]}],"ix":2},"a":{"a":0,"k":[39.02,38.831,0],"ix":1},"s":{"a":0,"k":[100,100,100],"ix":6}},"ao":0,"shapes":[{"ty":"gr","it":[{"ind":0,"ty":"sh","ix":1,"ks":{"a":1,"k":[{"i":{"x":0.833,"y":0.712},"o":{"x":0.167,"y":0},"t":1,"s":[{"i":[[-6.917,-9.748],[-0.918,-5.501],[1.145,-1.944],[5.591,11.541],[-0.396,22.865],[4.169,24.068],[-6.273,9.429]],"o":[[15.954,22.485],[6.113,36.634],[-6.067,10.301],[-2.82,-5.822],[0.422,-24.32],[-2.002,-11.56],[17.271,-25.96]],"v":[[29.037,-78.421],[27.138,-24.415],[27.088,70.824],[-17.099,74.153],[-30.327,-2.453],[-34.183,-39.786],[-26.562,-76.49]],"c":true}]},{"i":{"x":0.833,"y":1},"o":{"x":0.167,"y":0.288},"t":16.605,"s":[{"i":[[-6.917,-9.748],[-0.918,-5.501],[1.145,-1.944],[5.591,11.541],[-0.396,22.865],[4.169,24.068],[-6.273,9.429]],"o":[[15.954,22.485],[6.113,36.634],[-6.067,10.301],[-2.82,-5.822],[0.422,-24.32],[-2.002,-11.56],[17.271,-25.96]],"v":[[29.037,-78.421],[27.138,-24.415],[22.907,91.169],[-20.096,89.994],[-30.327,-2.453],[-34.183,-39.786],[-26.562,-76.49]],"c":true}]},{"i":{"x":0.833,"y":1},"o":{"x":0.167,"y":0},"t":31.633,"s":[{"i":[[-6.917,-9.748],[-0.918,-5.501],[1.145,-1.944],[5.591,11.541],[-0.396,22.865],[4.169,24.068],[-6.273,9.429]],"o":[[15.954,22.485],[6.113,36.634],[-6.067,10.301],[-2.82,-5.822],[0.422,-24.32],[-2.002,-11.56],[17.271,-25.96]],"v":[[29.037,-78.421],[27.138,-24.415],[27.088,70.824],[-17.099,74.153],[-30.327,-2.453],[-34.183,-39.786],[-26.562,-76.49]],"c":true}]},{"i":{"x":0.833,"y":0.712},"o":{"x":0.167,"y":0},"t":33.367,"s":[{"i":[[-6.917,-9.748],[-0.918,-5.501],[1.145,-1.944],[5.591,11.541],[-0.396,22.865],[4.169,24.068],[-6.273,9.429]],"o":[[15.954,22.485],[6.113,36.634],[-6.067,10.301],[-2.82,-5.822],[0.422,-24.32],[-2.002,-11.56],[17.271,-25.96]],"v":[[29.037,-78.421],[27.138,-24.415],[27.088,70.824],[-17.099,74.153],[-30.327,-2.453],[-34.183,-39.786],[-26.562,-76.49]],"c":true}]},{"i":{"x":0.833,"y":1},"o":{"x":0.167,"y":0.288},"t":48.395,"s":[{"i":[[-6.917,-9.748],[-0.918,-5.501],[1.145,-1.944],[5.591,11.541],[-0.396,22.865],[4.169,24.068],[-6.273,9.429]],"o":[[15.954,22.485],[6.113,36.634],[-6.067,10.301],[-2.82,-5.822],[0.422,-24.32],[-2.002,-11.56],[17.271,-25.96]],"v":[[29.037,-78.421],[27.138,-24.415],[22.907,91.169],[-20.096,89.994],[-30.327,-2.453],[-34.183,-39.786],[-26.562,-76.49]],"c":true}]},{"t":64,"s":[{"i":[[-6.917,-9.748],[-0.918,-5.501],[1.145,-1.944],[5.591,11.541],[-0.396,22.865],[4.169,24.068],[-6.273,9.429]],"o":[[15.954,22.485],[6.113,36.634],[-6.067,10.301],[-2.82,-5.822],[0.422,-24.32],[-2.002,-11.56],[17.271,-25.96]],"v":[[29.037,-78.421],[27.138,-24.415],[27.088,70.824],[-17.099,74.153],[-30.327,-2.453],[-34.183,-39.786],[-26.562,-76.49]],"c":true}]}],"ix":2},"nm":"Path 1","mn":"ADBE Vector Shape - Group","hd":false},{"ty":"fl","c":{"a":0,"k":[0.63,0.63,0.63,1],"ix":4},"o":{"a":0,"k":100,"ix":5},"r":1,"bm":0,"nm":"Fill 1","mn":"ADBE Vector Graphic - Fill","hd":false},{"ty":"tr","p":{"a":0,"k":[38.927,98.959],"ix":2},"a":{"a":0,"k":[0,0],"ix":1},"s":{"a":0,"k":[100,100],"ix":3},"r":{"a":0,"k":0,"ix":6},"o":{"a":0,"k":100,"ix":7},"sk":{"a":0,"k":0,"ix":4},"sa":{"a":0,"k":0,"ix":5},"nm":"Transform"}],"nm":"Group 2","np":2,"cix":2,"bm":0,"ix":1,"mn":"ADBE Vector Group","hd":false}],"ip":0,"op":111,"st":0,"bm":0},{"ddd":0,"ind":27,"ty":4,"nm":"Forearm_1","parent":28,"sr":1,"ks":{"o":{"a":0,"k":100,"ix":11},"r":{"a":1,"k":[{"i":{"x":[0.833],"y":[1]},"o":{"x":[0.333],"y":[0]},"t":1,"s":[167.946]},{"i":{"x":[0.667],"y":[1]},"o":{"x":[0.167],"y":[0]},"t":16.605,"s":[153.946]},{"i":{"x":[0.667],"y":[1]},"o":{"x":[0.333],"y":[0]},"t":31.633,"s":[167.946]},{"i":{"x":[0.833],"y":[1]},"o":{"x":[0.333],"y":[0]},"t":33.367,"s":[167.946]},{"i":{"x":[0.667],"y":[1]},"o":{"x":[0.167],"y":[0]},"t":48.395,"s":[153.946]},{"t":64,"s":[167.946]}],"ix":10},"p":{"a":0,"k":[20.462,68.941,0],"ix":2},"a":{"a":0,"k":[54.342,130.005,0],"ix":1},"s":{"a":0,"k":[-147.849,147.849,100],"ix":6}},"ao":0,"shapes":[{"ty":"gr","it":[{"ind":0,"ty":"sh","ix":1,"ks":{"a":0,"k":{"i":[[0.77,-9.675],[-5.853,-5.119],[-3.659,17.255],[15.029,25.24],[21.284,-13.108]],"o":[[-2.783,34.956],[1.026,0.897],[-6.179,-29.502],[-2.251,-3.78],[-0.198,0.122]],"v":[[-29.762,-41.657],[10.234,70.051],[33.12,59.861],[15.263,-49.21],[-24.037,-60.817]],"c":true},"ix":2},"nm":"Path 1","mn":"ADBE Vector Shape - Group","hd":false},{"ty":"fl","c":{"a":0,"k":[0.63,0.63,0.63,1],"ix":4},"o":{"a":0,"k":100,"ix":5},"r":1,"bm":0,"nm":"Fill 1","mn":"ADBE Vector Graphic - Fill","hd":false},{"ty":"tr","p":{"a":0,"k":[33.967,68.847],"ix":2},"a":{"a":0,"k":[0,0],"ix":1},"s":{"a":0,"k":[100,100],"ix":3},"r":{"a":0,"k":0,"ix":6},"o":{"a":0,"k":100,"ix":7},"sk":{"a":0,"k":0,"ix":4},"sa":{"a":0,"k":0,"ix":5},"nm":"Transform"}],"nm":"Group 2","np":2,"cix":2,"bm":0,"ix":1,"mn":"ADBE Vector Group","hd":false}],"ip":0,"op":111,"st":0,"bm":0},{"ddd":0,"ind":28,"ty":4,"nm":"hand_1","parent":1,"sr":1,"ks":{"o":{"a":0,"k":100,"ix":11},"r":{"a":0,"k":154.26,"ix":10},"p":{"a":0,"k":[143.203,2.682,0],"ix":2},"a":{"a":0,"k":[23.967,72.329,0],"ix":1},"s":{"a":0,"k":[-67.636,67.636,100],"ix":6}},"ao":0,"shapes":[{"ty":"gr","it":[{"ind":0,"ty":"sh","ix":1,"ks":{"a":0,"k":{"i":[[-0.438,0.193],[-1.202,-0.003],[0.28,-0.565],[-3.399,0.636],[-2.553,-2.332],[0.019,-0.211],[0.082,0.194],[-0.665,0.007],[-0.851,-3.55],[-0.203,-0.297],[-0.946,0.042],[-2.504,-0.781],[0.935,-5.407],[0.718,-3.74],[-0.814,-2.972],[-0.36,-1.124],[2.24,-3.373],[3.901,-2.26],[5.083,-0.286],[3.395,5.232],[1.019,5.64],[-0.998,8.526],[-0.041,4.57],[-0.637,1.573],[-0.979,0.717]],"o":[[1.097,-0.485],[0.317,0.001],[1.537,-3.098],[3.399,-0.636],[0.157,0.143],[-0.019,0.212],[-0.422,-0.996],[3.65,-0.036],[0.084,0.348],[0.678,0.993],[2.62,-0.119],[5.874,1.832],[-0.641,3.709],[-0.56,2.91],[0.312,1.139],[1.332,4.156],[-2.493,3.753],[-3.035,1.759],[-6.121,0.345],[-6.632,-10.223],[-1.525,-8.444],[0.529,-4.52],[0.015,-1.674],[0.455,-1.124],[0.392,-0.287]],"v":[[-26.155,-36.178],[-22.641,-36.866],[-18.01,-35.656],[-11.281,-42.04],[-1.658,-39.298],[-1.354,-38.765],[-1.009,-38.476],[6.038,-40.848],[14.034,-34.607],[14.387,-33.597],[17.965,-33.525],[25.771,-32.974],[32.057,-18.988],[28.632,-8.243],[27.56,0.873],[28.858,4.165],[25.061,16.891],[15.322,26.096],[-2.542,42.331],[-29.128,36.889],[-31.151,11.521],[-31.995,-14.122],[-30.323,-27.678],[-29.612,-32.626],[-27.405,-35.46]],"c":true},"ix":2},"nm":"Path 1","mn":"ADBE Vector Shape - Group","hd":false},{"ty":"fl","c":{"a":0,"k":[0.63,0.63,0.63,1],"ix":4},"o":{"a":0,"k":100,"ix":5},"r":1,"bm":0,"nm":"Fill 1","mn":"ADBE Vector Graphic - Fill","hd":false},{"ty":"tr","p":{"a":0,"k":[33.242,42.926],"ix":2},"a":{"a":0,"k":[0,0],"ix":1},"s":{"a":0,"k":[100,100],"ix":3},"r":{"a":0,"k":0,"ix":6},"o":{"a":0,"k":100,"ix":7},"sk":{"a":0,"k":0,"ix":4},"sa":{"a":0,"k":0,"ix":5},"nm":"Transform"}],"nm":"Group 1","np":2,"cix":2,"bm":0,"ix":1,"mn":"ADBE Vector Group","hd":false}],"ip":0,"op":111,"st":0,"bm":0}],"markers":[{"tm":110,"cm":"","dr":0}]}